{
  "Id": "34b5c0bd-da11-40c7-9998-582cc04bfaf0",
  "Nummer": "2024Z00631",
  "Soort": "Motie",
  "Titel": "Raad Algemene Zaken en Raad Buitenlandse Zaken ",
  "Citeertitel": null,
  "Alias": null,
  "Status": "Vrijgegeven",
  "Onderwerp": "Motie van het lid Tuinman c.s. over uitspreken dat de Tweede Kamer de beschuldiging van genocide verwerpt die nu bij het Internationale Gerechtshof tegen Israel is geuit",
  "GestartOp": "2024-01-18T00:00:00+01:00",
  "Organisatie": "Tweede Kamer",
  "Grondslagvoorhang": null,
  "Termijn": null,
  "Vergaderjaar": "2023-2024",
  "Volgnummer": 2799,
  "HuidigeBehandelstatus": null,
  "Afgedaan": true,
  "GrootProject": false,
  "GewijzigdOp": "2024-02-19T10:59:02.367+01:00",
  "ApiGewijzigdOp": "2024-02-19T15:42:35.1393821Z",
  "Verwijderd": false,
  "Kabinetsappreciatie": "Geen (expliciete) appreciatie",
  "Document": [
    {
      "Id": "43dd9192-9201-4b79-9e7f-158332aad3fc",
      "Soort": "Motie",
      "DocumentNummer": "2024D01486",
      "Titel": "Raad Algemene Zaken en Raad Buitenlandse Zaken ",
      "Onderwerp": "Motie van het lid Tuinman c.s. over uitspreken dat de Tweede Kamer de beschuldiging van genocide verwerpt die nu bij het Internationale Gerechtshof tegen Israel is geuit",
      "Datum": "2024-01-18T00:00:00+01:00",
      "Vergaderjaar": "2023-2024",
      "Kamer": 2,
      "Volgnummer": 2799,
      "Citeertitel": null,
      "Alias": null,
      "DatumRegistratie": "2024-01-18T00:00:00+01:00",
      "DatumOntvangst": null,
      "Aanhangselnummer": null,
      "KenmerkAfzender": null,
      "Organisatie": "Tweede Kamer",
      "ContentType": "application/pdf",
      "ContentLength": 21224,
      "GewijzigdOp": "2024-02-19T10:56:03.63+01:00",
      "ApiGewijzigdOp": "2024-02-20T14:06:23.7898229Z",
      "Verwijderd": false,
      "HuidigeDocumentVersie_Id": "7c06e1bb-68c7-4b19-b539-a59c2906dacd",
      "HuidigeDocumentVersie": {
        "Id": "7c06e1bb-68c7-4b19-b539-a59c2906dacd",
        "Status": "Vrijgegeven",
        "Versienummer": 4,
        "Bestandsgrootte": 36,
        "Extensie": ".pdf",
        "Datum": "2024-01-19T15:08:18.98+01:00",
        "GewijzigdOp": "2024-01-19T15:08:22.993+01:00",
        "ApiGewijzigdOp": "2024-01-19T14:09:26.2381608Z",
        "Verwijderd": false,
        "Document_Id": "43dd9192-9201-4b79-9e7f-158332aad3fc",
        "ExterneIdentifier": "kst-21501-02-2799",
        "DocumentPublicatie": [
          {
            "Id": "fdb7ad19-ede2-4c8d-916a-48424d095061",
            "Identifier": "kst-21501-02-2799",
            "DocumentType": "Pdf",
            "FileName": "kst-21501-02-2799.pdf",
            "Source": "Koop",
            "ContentLength": 36594,
            "ContentType": "application/pdf",
            "Url": "https://repository.overheid.nl/frbr/officielepublicaties/kst/21501-02/kst-21501-02-2799/1/pdf/kst-21501-02-2799.pdf",
            "PublicatieDatum": "2025-04-28T08:09:08.4566667+02:00",
            "GewijzigdOp": "2024-01-19T15:08:22.993+01:00",
            "ApiGewijzigdOp": "2025-05-03T20:10:07.867463Z",
            "Verwijderd": false,
            "DocumentVersie_Id": "7c06e1bb-68c7-4b19-b539-a59c2906dacd"
          },
          {
            "Id": "43256224-7f68-43da-8d8d-833d74cc8022",
            "Identifier": "kst-21501-02-2799",
            "DocumentType": "Xml",
            "FileName": "kst-21501-02-2799.xml",
            "Source": "Koop",
            "ContentLength": 2702,
            "ContentType": "application/xml",
            "Url": "https://repository.overheid.nl/frbr/officielepublicaties/kst/21501-02/kst-21501-02-2799/1/xml/kst-21501-02-2799.xml",
            "PublicatieDatum": "2025-04-28T08:09:08.4566667+02:00",
            "GewijzigdOp": "2024-01-19T15:08:22.993+01:00",
            "ApiGewijzigdOp": "2025-05-03T20:10:07.8474067Z",
            "Verwijderd": false,
            "DocumentVersie_Id": "7c06e1bb-68c7-4b19-b539-a59c2906dacd"
          },
          {
            "Id": "94ede139-c25a-446a-ac53-9ece25ed4224",
            "Identifier": "kst-21501-02-2799",
            "DocumentType": "Html",
            "FileName": "kst-21501-02-2799.html",
            "Source": "Koop",
            "ContentLength": 6143,
            "ContentType": "text/html",
            "Url": "https://repository.overheid.nl/frbr/officielepublicaties/kst/21501-02/kst-21501-02-2799/1/html/kst-21501-02-2799.html",
            "PublicatieDatum": "2025-04-28T08:09:08.4566667+02:00",
            "GewijzigdOp": "2024-01-19T15:08:22.993+01:00",
            "ApiGewijzigdOp": "2025-05-03T20:10:07.8331311Z",
            "Verwijderd": false,
            "DocumentVersie_Id": "7c06e1bb-68c7-4b19-b539-a59c2906dacd"
          },
          {
            "Id": "28558270-40fc-45db-b75d-bd5c4a7d2c19",
            "Identifier": "kst-21501-02-2799",
            "DocumentType": "Odt",
            "FileName": "kst-21501-02-2799.odt",
            "Source": "Koop",
            "ContentLength": 6946,
            "ContentType": "application/x-unknown-content-type",
            "Url": "https://repository.overheid.nl/frbr/officielepublicaties/kst/21501-02/kst-21501-02-2799/1/odt/kst-21501-02-2799.odt",
            "PublicatieDatum": "2025-04-28T08:09:08.4566667+02:00",
            "GewijzigdOp": "2024-01-19T15:08:22.993+01:00",
            "ApiGewijzigdOp": "2025-05-03T20:10:07.8521227Z",
            "Verwijderd": false,
            "DocumentVersie_Id": "7c06e1bb-68c7-4b19-b539-a59c2906dacd"
          }
        ],
        "DocumentPublicatieMetadata": [
          {
            "Id": "d103ee2c-4f63-427b-ad84-4076c2f6d191",
            "Identifier": "kst-21501-02-2799",
            "DocumentType": "Metadata",
            "FileName": "metadata.xml",
            "Source": "Koop",
            "ContentLength": 2567,
            "ContentType": "application/xml",
            "Url": "https://repository.overheid.nl/frbr/officielepublicaties/kst/21501-02/kst-21501-02-2799/1/metadata/metadata.xml",
            "PublicatieDatum": "2025-04-28T08:09:08.4566667+02:00",
            "GewijzigdOp": "2024-01-19T15:08:22.993+01:00",
            "ApiGewijzigdOp": "2025-05-03T20:10:07.8727701Z",
            "Verwijderd": false,
            "DocumentVersie_Id": "7c06e1bb-68c7-4b19-b539-a59c2906dacd"
          },
          {
            "Id": "eca09cc2-8463-457e-9134-f191cac14b33",
            "Identifier": "kst-21501-02-2799",
            "DocumentType": "Metadataowms",
            "FileName": "metadata_owms.xml",
            "Source": "Koop",
            "ContentLength": 2500,
            "ContentType": "application/xml",
            "Url": "https://repository.overheid.nl/frbr/officielepublicaties/kst/21501-02/kst-21501-02-2799/1/metadataowms/metadata_owms.xml",
            "PublicatieDatum": "2025-04-28T08:09:08.4566667+02:00",
            "GewijzigdOp": "2024-01-19T15:08:22.993+01:00",
            "ApiGewijzigdOp": "2025-05-03T20:10:07.887956Z",
            "Verwijderd": false,
            "DocumentVersie_Id": "7c06e1bb-68c7-4b19-b539-a59c2906dacd"
          }
        ]
      }
    }
  ]
}