{
  "Id": "64b93cd8-58c8-4510-9200-96dd214321e7",
  "Nummer": "2024Z17605",
  "Soort": "Motie",
  "Titel": "Arbeidsomstandigheden",
  "Citeertitel": null,
  "Alias": null,
  "Status": "Vrijgegeven",
  "Onderwerp": "Motie van de leden Patijn en Van Kent over werkgevers verplichten om mensen rechtstreeks in dienst te nemen en taallessen op B2-niveau aan te bieden als er gewerkt moet worden met gevaarlijke stoffen ",
  "GestartOp": "2024-11-06T00:00:00+01:00",
  "Organisatie": "Tweede Kamer",
  "Grondslagvoorhang": null,
  "Termijn": null,
  "Vergaderjaar": "2024-2025",
  "Volgnummer": 510,
  "HuidigeBehandelstatus": null,
  "Afgedaan": true,
  "GrootProject": false,
  "GewijzigdOp": "2024-11-12T17:10:51.95+01:00",
  "ApiGewijzigdOp": "2024-11-19T10:34:38.1757657Z",
  "Verwijderd": false,
  "Kabinetsappreciatie": "Ontraden",
  "Document": [
    {
      "Id": "3b58b929-aa1d-421c-97b6-48fb0a29e4ae",
      "Soort": "Motie",
      "DocumentNummer": "2024D42394",
      "Titel": "Arbeidsomstandigheden",
      "Onderwerp": "Motie van de leden Patijn en Van Kent over werkgevers verplichten om mensen rechtstreeks in dienst te nemen en taallessen op B2-niveau aan te bieden als er gewerkt moet worden met gevaarlijke stoffen ",
      "Datum": "2024-11-06T00:00:00+01:00",
      "Vergaderjaar": "2024-2025",
      "Kamer": 2,
      "Volgnummer": 510,
      "Citeertitel": null,
      "Alias": null,
      "DatumRegistratie": "2024-11-06T00:00:00+01:00",
      "DatumOntvangst": null,
      "Aanhangselnummer": null,
      "KenmerkAfzender": null,
      "Organisatie": "Tweede Kamer",
      "ContentType": "application/pdf",
      "ContentLength": 20728,
      "GewijzigdOp": "2024-11-19T11:33:18.28+01:00",
      "ApiGewijzigdOp": "2024-11-19T10:34:38.1445106Z",
      "Verwijderd": false,
      "HuidigeDocumentVersie_Id": "52f5caa1-6d7a-4469-ba55-93b0ed1a033e",
      "HuidigeDocumentVersie": {
        "Id": "52f5caa1-6d7a-4469-ba55-93b0ed1a033e",
        "Status": "Vrijgegeven",
        "Versienummer": 3,
        "Bestandsgrootte": 36,
        "Extensie": ".pdf",
        "Datum": "2024-11-19T11:33:15.12+01:00",
        "GewijzigdOp": "2024-11-19T11:33:18.28+01:00",
        "ApiGewijzigdOp": "2024-11-19T10:33:52.8219144Z",
        "Verwijderd": false,
        "Document_Id": "3b58b929-aa1d-421c-97b6-48fb0a29e4ae",
        "ExterneIdentifier": "kst-25883-510",
        "DocumentPublicatie": [
          {
            "Id": "963348f9-7a19-4718-afd4-15605e2205c3",
            "Identifier": "kst-25883-510",
            "DocumentType": "Xml",
            "FileName": "kst-25883-510.xml",
            "Source": "Koop",
            "ContentLength": 2337,
            "ContentType": "application/xml",
            "Url": null,
            "PublicatieDatum": "2025-04-25T08:30:56.51+02:00",
            "GewijzigdOp": "2024-11-19T11:33:18.28+01:00",
            "ApiGewijzigdOp": "2025-04-26T03:59:14.8564655Z",
            "Verwijderd": false,
            "DocumentVersie_Id": "52f5caa1-6d7a-4469-ba55-93b0ed1a033e"
          },
          {
            "Id": "6b7ec02e-b2fe-474c-91b4-4d49fedc9107",
            "Identifier": "kst-25883-510",
            "DocumentType": "Html",
            "FileName": "kst-25883-510.html",
            "Source": "Koop",
            "ContentLength": 5521,
            "ContentType": "text/html",
            "Url": null,
            "PublicatieDatum": "2025-04-25T08:30:56.51+02:00",
            "GewijzigdOp": "2024-11-19T11:33:18.28+01:00",
            "ApiGewijzigdOp": "2025-04-26T03:59:14.8515143Z",
            "Verwijderd": false,
            "DocumentVersie_Id": "52f5caa1-6d7a-4469-ba55-93b0ed1a033e"
          },
          {
            "Id": "518b26a6-135f-4220-9eb9-9fcd836542f4",
            "Identifier": "kst-25883-510",
            "DocumentType": "Pdf",
            "FileName": "kst-25883-510.pdf",
            "Source": "Koop",
            "ContentLength": 36095,
            "ContentType": "application/pdf",
            "Url": null,
            "PublicatieDatum": "2025-04-25T08:30:56.51+02:00",
            "GewijzigdOp": "2024-11-19T11:33:18.28+01:00",
            "ApiGewijzigdOp": "2025-04-26T03:59:14.8660029Z",
            "Verwijderd": false,
            "DocumentVersie_Id": "52f5caa1-6d7a-4469-ba55-93b0ed1a033e"
          },
          {
            "Id": "2a54885a-804d-4e0b-92f2-bcc53a1bf8aa",
            "Identifier": "kst-25883-510",
            "DocumentType": "Odt",
            "FileName": "kst-25883-510.odt",
            "Source": "Koop",
            "ContentLength": 6809,
            "ContentType": "application/x-unknown-content-type",
            "Url": null,
            "PublicatieDatum": "2025-04-25T08:30:56.51+02:00",
            "GewijzigdOp": "2024-11-19T11:33:18.28+01:00",
            "ApiGewijzigdOp": "2025-04-26T03:59:14.8612164Z",
            "Verwijderd": false,
            "DocumentVersie_Id": "52f5caa1-6d7a-4469-ba55-93b0ed1a033e"
          }
        ],
        "DocumentPublicatieMetadata": [
          {
            "Id": "376599a3-6c4b-4e4e-a43d-581aa7cbefaa",
            "Identifier": "kst-25883-510",
            "DocumentType": "Metadata",
            "FileName": "metadata.xml",
            "Source": "Koop",
            "ContentLength": 2403,
            "ContentType": "application/xml",
            "Url": null,
            "PublicatieDatum": "2025-04-25T08:30:56.51+02:00",
            "GewijzigdOp": "2024-11-19T11:33:18.28+01:00",
            "ApiGewijzigdOp": "2025-04-26T03:59:14.8709726Z",
            "Verwijderd": false,
            "DocumentVersie_Id": "52f5caa1-6d7a-4469-ba55-93b0ed1a033e"
          },
          {
            "Id": "2b1cb9db-aa28-4d0e-9624-b4219b5881f2",
            "Identifier": "kst-25883-510",
            "DocumentType": "Metadataowms",
            "FileName": "metadata_owms.xml",
            "Source": "Koop",
            "ContentLength": 2356,
            "ContentType": "application/xml",
            "Url": null,
            "PublicatieDatum": "2025-04-25T08:30:56.51+02:00",
            "GewijzigdOp": "2024-11-19T11:33:18.28+01:00",
            "ApiGewijzigdOp": "2025-04-26T03:59:29.3683911Z",
            "Verwijderd": false,
            "DocumentVersie_Id": "52f5caa1-6d7a-4469-ba55-93b0ed1a033e"
          }
        ]
      }
    }
  ]
}