{
  "Id": "a42df053-5e75-4589-80ff-1e8be7e7bceb",
  "Nummer": "2025Z04989",
  "Soort": "Motie",
  "Titel": "Europese Raad",
  "Citeertitel": null,
  "Alias": null,
  "Status": "Vrijgegeven",
  "Onderwerp": "Motie van het lid Timmermans c.s. over het financieringstekort van Radio Free Europe Europees dichten ",
  "GestartOp": "2025-03-18T00:00:00+01:00",
  "Organisatie": "Tweede Kamer",
  "Grondslagvoorhang": null,
  "Termijn": null,
  "Vergaderjaar": "2024-2025",
  "Volgnummer": 2221,
  "HuidigeBehandelstatus": null,
  "Afgedaan": true,
  "GrootProject": false,
  "GewijzigdOp": "2025-03-19T14:47:57.963+01:00",
  "ApiGewijzigdOp": "2025-06-06T14:24:03.9890356Z",
  "Verwijderd": false,
  "Kabinetsappreciatie": "Oordeel Kamer",
  "Document": [
    {
      "Id": "6abba815-b28c-4b86-a2a0-3968ba195bcd",
      "Soort": "Motie",
      "DocumentNummer": "2025D11585",
      "Titel": "Europese Raad",
      "Onderwerp": "Motie van het lid Timmermans c.s. over het financieringstekort van Radio Free Europe Europees dichten ",
      "Datum": "2025-03-18T00:00:00+01:00",
      "Vergaderjaar": "2024-2025",
      "Kamer": 2,
      "Volgnummer": 2221,
      "Citeertitel": null,
      "Alias": null,
      "DatumRegistratie": "2025-03-18T00:00:00+01:00",
      "DatumOntvangst": null,
      "Aanhangselnummer": null,
      "KenmerkAfzender": null,
      "Organisatie": "Tweede Kamer",
      "ContentType": "application/pdf",
      "ContentLength": 20566,
      "GewijzigdOp": "2025-03-19T12:06:57.897+01:00",
      "ApiGewijzigdOp": "2025-03-19T11:07:27.3325335Z",
      "Verwijderd": false,
      "HuidigeDocumentVersie_Id": "50e42ca8-6f53-4150-9f80-1e0f04a4f490",
      "HuidigeDocumentVersie": {
        "Id": "50e42ca8-6f53-4150-9f80-1e0f04a4f490",
        "Status": "Vrijgegeven",
        "Versienummer": 3,
        "Bestandsgrootte": 35,
        "Extensie": ".pdf",
        "Datum": "2025-03-19T12:06:50.47+01:00",
        "GewijzigdOp": "2025-03-19T12:06:57.897+01:00",
        "ApiGewijzigdOp": "2025-03-19T11:07:03.1676113Z",
        "Verwijderd": false,
        "Document_Id": "6abba815-b28c-4b86-a2a0-3968ba195bcd",
        "ExterneIdentifier": "kst-21501-20-2221",
        "DocumentPublicatie": [
          {
            "Id": "e742d8cc-8d9f-4665-8753-7a749b8f0f5d",
            "Identifier": "kst-21501-20-2221",
            "DocumentType": "Html",
            "FileName": "kst-21501-20-2221.html",
            "Source": "Koop",
            "ContentLength": 5701,
            "ContentType": "text/html",
            "Url": null,
            "PublicatieDatum": "2025-03-19T11:06:59.2962655+01:00",
            "GewijzigdOp": "2025-03-19T12:06:57.897+01:00",
            "ApiGewijzigdOp": "2025-03-19T11:07:07.3858283Z",
            "Verwijderd": false,
            "DocumentVersie_Id": "50e42ca8-6f53-4150-9f80-1e0f04a4f490"
          },
          {
            "Id": "762eedb1-20cb-456f-babc-9ae3ca72e4a8",
            "Identifier": "kst-21501-20-2221",
            "DocumentType": "Xml",
            "FileName": "kst-21501-20-2221.xml",
            "Source": "Koop",
            "ContentLength": 2171,
            "ContentType": "application/xml",
            "Url": null,
            "PublicatieDatum": "2025-03-19T11:06:59.2971344+01:00",
            "GewijzigdOp": "2025-03-19T12:06:57.897+01:00",
            "ApiGewijzigdOp": "2025-03-19T11:07:07.4605069Z",
            "Verwijderd": false,
            "DocumentVersie_Id": "50e42ca8-6f53-4150-9f80-1e0f04a4f490"
          },
          {
            "Id": "716d6a86-cba2-4d3a-8e99-c18b2be2f6ed",
            "Identifier": "kst-21501-20-2221",
            "DocumentType": "Odt",
            "FileName": "kst-21501-20-2221.odt",
            "Source": "Koop",
            "ContentLength": 6749,
            "ContentType": "application/x-unknown-content-type",
            "Url": null,
            "PublicatieDatum": "2025-03-19T11:06:59.2979128+01:00",
            "GewijzigdOp": "2025-03-19T12:06:57.897+01:00",
            "ApiGewijzigdOp": "2025-03-19T11:07:08.948441Z",
            "Verwijderd": false,
            "DocumentVersie_Id": "50e42ca8-6f53-4150-9f80-1e0f04a4f490"
          },
          {
            "Id": "363b57ff-9d1b-401b-9e36-d280cc4cdbf4",
            "Identifier": "kst-21501-20-2221",
            "DocumentType": "Pdf",
            "FileName": "kst-21501-20-2221.pdf",
            "Source": "Koop",
            "ContentLength": 35834,
            "ContentType": "application/pdf",
            "Url": null,
            "PublicatieDatum": "2025-03-19T11:06:59.298715+01:00",
            "GewijzigdOp": "2025-03-19T12:06:57.897+01:00",
            "ApiGewijzigdOp": "2025-03-19T11:07:09.9567594Z",
            "Verwijderd": false,
            "DocumentVersie_Id": "50e42ca8-6f53-4150-9f80-1e0f04a4f490"
          }
        ],
        "DocumentPublicatieMetadata": [
          {
            "Id": "2cb59c47-9d45-4d2f-bce4-3f6fb4475391",
            "Identifier": "kst-21501-20-2221",
            "DocumentType": "Metadataowms",
            "FileName": "metadata_owms.xml",
            "Source": "Koop",
            "ContentLength": 2682,
            "ContentType": "application/xml",
            "Url": null,
            "PublicatieDatum": "2025-03-19T11:06:59.3002046+01:00",
            "GewijzigdOp": "2025-03-19T12:06:57.897+01:00",
            "ApiGewijzigdOp": "2025-03-19T11:07:09.9764066Z",
            "Verwijderd": false,
            "DocumentVersie_Id": "50e42ca8-6f53-4150-9f80-1e0f04a4f490"
          },
          {
            "Id": "9d70bcb7-b187-4a01-bbaa-49b150f161e6",
            "Identifier": "kst-21501-20-2221",
            "DocumentType": "Metadata",
            "FileName": "metadata.xml",
            "Source": "Koop",
            "ContentLength": 2809,
            "ContentType": "application/xml",
            "Url": null,
            "PublicatieDatum": "2025-03-19T11:06:59.2994849+01:00",
            "GewijzigdOp": "2025-03-19T12:06:57.897+01:00",
            "ApiGewijzigdOp": "2025-03-19T11:07:09.9642928Z",
            "Verwijderd": false,
            "DocumentVersie_Id": "50e42ca8-6f53-4150-9f80-1e0f04a4f490"
          }
        ]
      }
    }
  ]
}