{
  "Id": "b0ea5eea-966f-4a22-871e-3dbf39166ff4",
  "Nummer": "2025Z17465",
  "Soort": "Motie",
  "Titel": "Initiatiefnota van het lid Koekkoek over Alle Seinen op Groen ",
  "Citeertitel": null,
  "Alias": null,
  "Status": "Vrijgegeven",
  "Onderwerp": "Motie van het lid Veltman over het Besluit capaciteitsverdeling aanpassen met het oog op juridisch bindende kaderovereenkomsten die vervoerders meerjarige zekerheid geven ",
  "GestartOp": "2025-09-22T00:00:00+02:00",
  "Organisatie": "Tweede Kamer",
  "Grondslagvoorhang": null,
  "Termijn": null,
  "Vergaderjaar": "2025-2026",
  "Volgnummer": 11,
  "HuidigeBehandelstatus": null,
  "Afgedaan": true,
  "GrootProject": false,
  "GewijzigdOp": "2025-09-30T16:20:08.82+02:00",
  "ApiGewijzigdOp": "2025-09-30T14:20:16.3773117Z",
  "Verwijderd": false,
  "Kabinetsappreciatie": "Oordeel Kamer",
  "Document": [
    {
      "Id": "a7c7e797-e108-4fd5-9dd3-7442e3dcde5a",
      "Soort": "Motie",
      "DocumentNummer": "2025D40709",
      "Titel": "Initiatiefnota van het lid Koekkoek over Alle Seinen op Groen ",
      "Onderwerp": "Motie van het lid Veltman over het Besluit capaciteitsverdeling aanpassen met het oog op juridisch bindende kaderovereenkomsten die vervoerders meerjarige zekerheid geven ",
      "Datum": "2025-09-22T00:00:00+02:00",
      "Vergaderjaar": "2025-2026",
      "Kamer": 2,
      "Volgnummer": 11,
      "Citeertitel": null,
      "Alias": null,
      "DatumRegistratie": "2025-09-22T00:00:00+02:00",
      "DatumOntvangst": null,
      "Aanhangselnummer": null,
      "KenmerkAfzender": null,
      "Organisatie": "Tweede Kamer",
      "ContentType": "application/pdf",
      "ContentLength": 20440,
      "GewijzigdOp": "2025-09-23T11:11:55.657+02:00",
      "ApiGewijzigdOp": "2025-09-23T09:12:27.5901497Z",
      "Verwijderd": false,
      "HuidigeDocumentVersie_Id": "eca493de-5794-443a-8ca5-e2d80215ebdf",
      "HuidigeDocumentVersie": {
        "Id": "eca493de-5794-443a-8ca5-e2d80215ebdf",
        "Status": "Vrijgegeven",
        "Versienummer": 3,
        "Bestandsgrootte": 35,
        "Extensie": ".pdf",
        "Datum": "2025-09-23T11:11:49.84+02:00",
        "GewijzigdOp": "2025-09-23T11:11:55.657+02:00",
        "ApiGewijzigdOp": "2025-09-23T09:12:01.8061196Z",
        "Verwijderd": false,
        "Document_Id": "a7c7e797-e108-4fd5-9dd3-7442e3dcde5a",
        "ExterneIdentifier": "kst-36563-11",
        "DocumentPublicatie": [
          {
            "Id": "31eeb8a1-6103-4018-a1f7-1243c62ae681",
            "Identifier": "kst-36563-11",
            "DocumentType": "Pdf",
            "FileName": "kst-36563-11.pdf",
            "Source": "Koop",
            "ContentLength": 35816,
            "ContentType": "application/pdf",
            "Url": null,
            "PublicatieDatum": "2025-09-23T09:11:57.5337484+02:00",
            "GewijzigdOp": "2025-09-23T11:11:55.657+02:00",
            "ApiGewijzigdOp": "2025-09-23T09:12:01.8995642Z",
            "Verwijderd": false,
            "DocumentVersie_Id": "eca493de-5794-443a-8ca5-e2d80215ebdf"
          },
          {
            "Id": "162d409d-56b5-4342-afa7-9deb70cd6cfe",
            "Identifier": "kst-36563-11",
            "DocumentType": "Odt",
            "FileName": "kst-36563-11.odt",
            "Source": "Koop",
            "ContentLength": 6986,
            "ContentType": "application/x-unknown-content-type",
            "Url": null,
            "PublicatieDatum": "2025-09-23T09:11:57.5327659+02:00",
            "GewijzigdOp": "2025-09-23T11:11:55.657+02:00",
            "ApiGewijzigdOp": "2025-09-23T09:12:01.893218Z",
            "Verwijderd": false,
            "DocumentVersie_Id": "eca493de-5794-443a-8ca5-e2d80215ebdf"
          },
          {
            "Id": "0da55099-a52e-49eb-a201-cef2994c8648",
            "Identifier": "kst-36563-11",
            "DocumentType": "Html",
            "FileName": "kst-36563-11.html",
            "Source": "Koop",
            "ContentLength": 6072,
            "ContentType": "text/html",
            "Url": null,
            "PublicatieDatum": "2025-09-23T09:11:57.5218047+02:00",
            "GewijzigdOp": "2025-09-23T11:11:55.657+02:00",
            "ApiGewijzigdOp": "2025-09-23T09:12:01.8802169Z",
            "Verwijderd": false,
            "DocumentVersie_Id": "eca493de-5794-443a-8ca5-e2d80215ebdf"
          },
          {
            "Id": "6778ddcd-1a17-4aba-887f-d8dc1acff762",
            "Identifier": "kst-36563-11",
            "DocumentType": "Xml",
            "FileName": "kst-36563-11.xml",
            "Source": "Koop",
            "ContentLength": 5134,
            "ContentType": "application/xml",
            "Url": null,
            "PublicatieDatum": "2025-09-23T09:11:57.5270061+02:00",
            "GewijzigdOp": "2025-09-23T11:11:55.657+02:00",
            "ApiGewijzigdOp": "2025-09-23T09:12:01.8871143Z",
            "Verwijderd": false,
            "DocumentVersie_Id": "eca493de-5794-443a-8ca5-e2d80215ebdf"
          }
        ],
        "DocumentPublicatieMetadata": [
          {
            "Id": "73e48eec-572d-4022-9157-bf171bd7407d",
            "Identifier": "kst-36563-11",
            "DocumentType": "Metadataowms",
            "FileName": "metadata_owms.xml",
            "Source": "Koop",
            "ContentLength": 2304,
            "ContentType": "application/xml",
            "Url": null,
            "PublicatieDatum": "2025-09-23T09:11:57.5353384+02:00",
            "GewijzigdOp": "2025-09-23T11:11:55.657+02:00",
            "ApiGewijzigdOp": "2025-09-23T09:12:01.9135042Z",
            "Verwijderd": false,
            "DocumentVersie_Id": "eca493de-5794-443a-8ca5-e2d80215ebdf"
          },
          {
            "Id": "ca0adebb-bb9f-4d69-9eac-cb1dc7cca62f",
            "Identifier": "kst-36563-11",
            "DocumentType": "Metadata",
            "FileName": "metadata.xml",
            "Source": "Koop",
            "ContentLength": 2341,
            "ContentType": "application/xml",
            "Url": null,
            "PublicatieDatum": "2025-09-23T09:11:57.5345326+02:00",
            "GewijzigdOp": "2025-09-23T11:11:55.657+02:00",
            "ApiGewijzigdOp": "2025-09-23T09:12:01.9062018Z",
            "Verwijderd": false,
            "DocumentVersie_Id": "eca493de-5794-443a-8ca5-e2d80215ebdf"
          }
        ]
      }
    }
  ]
}