<?xml version="1.0" encoding="UTF-8"?>
<officiele-publicatie xsi:noNamespaceSchemaLocation="http://technische-documentatie.oep.overheid.nl/repository/schemas/op-consolidated/op-consolidated_2014-05-15/xsd/op-xsd-2014-05-15.xsd" xmlns:xsi="http://www.w3.org/2001/XMLSchema-instance">
  <metadata>
    <meta name="OVERHEIDop.externMetadataRecord" scheme="" content="https://zoek.officielebekendmakingen.nl/kst-31293-744/metadata.xml"/>
  </metadata>
  <kamerstuk>
    <kamerstukkop>
      <tekstregel inhoud="vergaderjaar">Vergaderjaar 2023-2024</tekstregel>
      <tekstregel inhoud="kameraanduiding">Tweede Kamer der Staten-Generaal</tekstregel>
      <tekstregel inhoud="kamernummer">2</tekstregel>
      <tekstregel inhoud="documenttype">Kamerstukken</tekstregel>
    </kamerstukkop>
    <dossier>
      <dossiernummer>
        <dossiernr>31 293</dossiernr>
      </dossiernummer>
      <titel>Primair Onderwijs</titel>
    </dossier>
    <stuk>
      <stuknr>Nr. <ondernummer kamer="2">744</ondernummer></stuknr>
      <titel>MOTIE VAN HET LID SOEPBOER</titel>
      <datumtekst>Voorgesteld <datum isodatum="2024-09-04">4 september 2024</datum></datumtekst>
      <algemeen>
        <vrije-tekst>
          <tekst status="goed">
            <al>De Kamer,</al>
            <al>gehoord de beraadslaging,</al>
            <al>constaterende dat er op dit moment sprake is van gedeelde financiering en gedeelde verantwoordelijkheid als het gaat om het vormgeven van vve;</al>
            <al>constaterende dat gemeenten en onderwijs samen afspraken moeten maken, nakomen en evalueren om vve goed te kunnen laten functioneren;</al>
            <al>constaterende dat slechts in 56 van de 342 gemeenten dat goed gebeurt;</al>
            <al>overwegende dat de inspectie gemeenten in haar toezicht alleen kan aanspreken op de vraag of ze resultaatafspraken maken, maar geen formele mogelijkheid heeft om te sturen op de evaluatie of de inhoud daarvan;</al>
            <al>verzoekt de regering maatregelen te treffen zodat er ook een juridische verplichting komt voor het evalueren van de afspraken en de inspectie ook kan sturen op de evaluatie daarvan,</al>
            <al>en gaat over tot de orde van de dag.</al>
            <al>Soepboer</al>
          </tekst>
        </vrije-tekst>
      </algemeen>
    </stuk>
  </kamerstuk>
</officiele-publicatie>