<?xml version="1.0" encoding="UTF-8"?>
<officiele-publicatie xsi:noNamespaceSchemaLocation="http://technische-documentatie.oep.overheid.nl/repository/schemas/op-consolidated/op-consolidated_2014-05-15/xsd/op-xsd-2014-05-15.xsd" xmlns:xsi="http://www.w3.org/2001/XMLSchema-instance">
  <metadata>
    <meta name="OVERHEIDop.externMetadataRecord" scheme="" content="https://zoek.officielebekendmakingen.nl/kst-33836-118/metadata.xml"/>
  </metadata>
  <kamerstuk>
    <kamerstukkop>
      <tekstregel inhoud="vergaderjaar">Vergaderjaar 2024-2025</tekstregel>
      <tekstregel inhoud="kameraanduiding">Tweede Kamer der Staten-Generaal</tekstregel>
      <tekstregel inhoud="kamernummer">2</tekstregel>
      <tekstregel inhoud="documenttype">Kamerstukken</tekstregel>
    </kamerstukkop>
    <dossier>
      <dossiernummer>
        <dossiernr>33 836</dossiernr>
      </dossiernummer>
      <titel>Personen- en familierecht</titel>
    </dossier>
    <stuk>
      <stuknr>Nr. <ondernummer kamer="2">118</ondernummer></stuknr>
      <titel>MOTIE VAN HET LID SNELLER</titel>
      <datumtekst>Voorgesteld <datum isodatum="2025-04-03">3 april 2025</datum></datumtekst>
      <algemeen>
        <vrije-tekst>
          <tekst status="goed">
            <al>De Kamer,</al>
            <al>gehoord de beraadslaging,</al>
            <al>constaterende dat een wettelijke regeling voor meerouderschap en meeroudergezag in het belang is van het kind;</al>
            <al>constaterende dat een op de vijf meeroudergezinnen problemen ervaart met het ontbreken van zo'n regeling;</al>
            <al>constaterende dat de Kamer al in 2022 vroeg om een concreet stappenplan en dat dat er nog steeds niet is;</al>
            <al>constaterende dat er geen stelselwijzigingen nodig zijn wanneer zo veel mogelijk wordt aangesloten bij bestaande regelingen;</al>
            <al>van mening dat er hiermee geen juridische of uitvoeringstechnische barrières meer zijn voor meerouderschap en meeroudergezag;</al>
            <al>verzoekt de regering om bij alle wets- en beleidswijzigingen, inclusief verzamelwetten, waarbij een ouder-kindrelatie een rol speelt, de wettekst of beleidsregel alvast geschikt te formuleren voor meerouderschap en meeroudergezag,</al>
            <al>en gaat over tot de orde van de dag.</al>
            <al>Sneller</al>
          </tekst>
        </vrije-tekst>
      </algemeen>
    </stuk>
  </kamerstuk>
</officiele-publicatie>