<?xml version="1.0" encoding="UTF-8"?>
<officiele-publicatie xsi:noNamespaceSchemaLocation="http://technische-documentatie.oep.overheid.nl/repository/schemas/op-consolidated/op-consolidated_2014-05-15/xsd/op-xsd-2014-05-15.xsd" xmlns:xsi="http://www.w3.org/2001/XMLSchema-instance">
  <metadata>
    <meta name="OVERHEIDop.externMetadataRecord" scheme="" content="https://zoek.officielebekendmakingen.nl/kst-26643-1256/metadata.xml"/>
  </metadata>
  <kamerstuk>
    <kamerstukkop>
      <tekstregel inhoud="vergaderjaar">Vergaderjaar 2024-2025</tekstregel>
      <tekstregel inhoud="kameraanduiding">Tweede Kamer der Staten-Generaal</tekstregel>
      <tekstregel inhoud="kamernummer">2</tekstregel>
      <tekstregel inhoud="documenttype">Kamerstukken</tekstregel>
    </kamerstukkop>
    <dossier>
      <dossiernummer>
        <dossiernr>26 643</dossiernr>
      </dossiernummer>
      <titel>Informatie- en communicatietechnologie (ICT)</titel>
    </dossier>
    <stuk>
      <stuknr>Nr. <ondernummer kamer="2">1256</ondernummer></stuknr>
      <titel>MOTIE VAN DE LEDEN CHAKOR EN KATHMANN</titel>
      <datumtekst>Voorgesteld <datum isodatum="2024-12-11">11 december 2024</datum></datumtekst>
      <algemeen>
        <vrije-tekst>
          <tekst status="goed">
            <al>De Kamer,</al>
            <al>gehoord de beraadslaging,</al>
            <al>overwegende dat overheid en samenleving verregaand afhankelijk zijn van digitale processen;</al>
            <al>overwegende dat het bij langdurige uitval van digitale processen van belang is dat er alternatieve manieren van dienstverlening blijven bestaan;</al>
            <al>constaterende dat het uitvallen van digitale processen, bijvoorbeeld als gevolg van de CrowdStrike- en NAFIN-storingen, meermaals tot problemen in de dienstverlening van overheid en vitale sectoren heeft geleid;</al>
            <al>verzoekt de regering om samen met overheden en vitale sectoren plannen te ontwikkelen om essentiële dienstverlening in geval van een grootschalige digitale storing zo veel mogelijk in stand te houden,</al>
            <al>en gaat over tot de orde van de dag.</al>
            <al-groep>
              <al>Chakor</al>
              <al>Kathmann</al>
            </al-groep>
          </tekst>
        </vrije-tekst>
      </algemeen>
    </stuk>
  </kamerstuk>
</officiele-publicatie>