<?xml version="1.0" encoding="UTF-8"?>
<officiele-publicatie xsi:noNamespaceSchemaLocation="http://technische-documentatie.oep.overheid.nl/repository/schemas/op-consolidated/op-consolidated_2014-05-15/xsd/op-xsd-2014-05-15.xsd" xmlns:xsi="http://www.w3.org/2001/XMLSchema-instance">
  <metadata>
    <meta name="OVERHEIDop.externMetadataRecord" scheme="" content="https://zoek.officielebekendmakingen.nl/kst-36600-V-43/metadata.xml"/>
  </metadata>
  <kamerstuk>
    <kamerstukkop>
      <tekstregel inhoud="vergaderjaar">Vergaderjaar 2024-2025</tekstregel>
      <tekstregel inhoud="kameraanduiding">Tweede Kamer der Staten-Generaal</tekstregel>
      <tekstregel inhoud="kamernummer">2</tekstregel>
      <tekstregel inhoud="documenttype">Kamerstukken</tekstregel>
    </kamerstukkop>
    <dossier>
      <dossiernummer>
        <dossiernr>36 600</dossiernr>
        <begrotingshoofdstuk>V</begrotingshoofdstuk>
      </dossiernummer>
      <titel>Vaststelling van de begrotingsstaat van het Ministerie van Buitenlandse Zaken (V) voor het jaar 2025</titel>
    </dossier>
    <stuk>
      <stuknr>Nr. <ondernummer kamer="2">43</ondernummer></stuknr>
      <titel>MOTIE VAN HET LID DEKKER</titel>
      <datumtekst>Voorgesteld <datum isodatum="2024-11-21">21 november 2024</datum></datumtekst>
      <algemeen>
        <vrije-tekst>
          <tekst status="goed">
            <al>De Kamer,</al>
            <al>gehoord de beraadslaging,</al>
            <al>overwegende dat Oekraïne de strijd tegen Rusland zeker niet zal winnen en dat de uiteindelijke uitkomst van dit conflict de facto zal worden gedicteerd door de Russen;</al>
            <al>overwegende dat de Verenigde Staten zich onder Trump op de een of andere manier op korte termijn uit dit conflict zullen terugtrekken, wellicht in de vorm van een goeddeels door Rusland gedicteerde vredesovereenkomst;</al>
            <al>overwegende dat iedere poging van Europa om in militaire zin een verschil te maken in dit conflict niet alleen futiel, wereldvreemd en belachelijk is, maar bovenal bijzonder gevaarlijk;</al>
            <al>roept de regering op om, los van de huidige Atlantische consensus, met betrekking tot de Rusland-Oekraïneproblematiek – al was het maar als ware het een plan B-scenario – een realistisch en eigen buitenlandbeleid te ontwikkelen dat het Nederlands belang op de eerste plaats stelt,</al>
            <al>en gaat over tot de orde van de dag.</al>
            <al>Dekker</al>
          </tekst>
        </vrije-tekst>
      </algemeen>
    </stuk>
  </kamerstuk>
</officiele-publicatie>