<?xml version="1.0" encoding="UTF-8"?>
<officiele-publicatie xsi:noNamespaceSchemaLocation="http://technische-documentatie.oep.overheid.nl/repository/schemas/op-consolidated/op-consolidated_2014-05-15/xsd/op-xsd-2014-05-15.xsd" xmlns:xsi="http://www.w3.org/2001/XMLSchema-instance">
  <metadata>
    <meta name="OVERHEIDop.externMetadataRecord" scheme="" content="https://zoek.officielebekendmakingen.nl/kst-31524-610/metadata.xml"/>
  </metadata>
  <kamerstuk>
    <kamerstukkop>
      <tekstregel inhoud="vergaderjaar">Vergaderjaar 2023-2024</tekstregel>
      <tekstregel inhoud="kameraanduiding">Tweede Kamer der Staten-Generaal</tekstregel>
      <tekstregel inhoud="kamernummer">2</tekstregel>
      <tekstregel inhoud="documenttype">Kamerstukken</tekstregel>
    </kamerstukkop>
    <dossier>
      <dossiernummer>
        <dossiernr>31 524</dossiernr>
      </dossiernummer>
      <titel>Beroepsonderwijs en Volwassenen Educatie</titel>
    </dossier>
    <stuk>
      <stuknr>Nr. <ondernummer kamer="2">610</ondernummer></stuknr>
      <titel>MOTIE VAN HET LID TSEGGAI</titel>
      <datumtekst>Voorgesteld <datum isodatum="2024-05-21">21 mei 2024</datum></datumtekst>
      <algemeen>
        <vrije-tekst>
          <tekst status="goed">
            <al>De Kamer,</al>
            <al>gehoord de beraadslaging,</al>
            <al>constaterende dat in de recent gepubliceerde Staat van het Onderwijs zorgen worden geuit over de onderwijskwaliteit in Nederland, waaronder het mbo;</al>
            <al>constaterende dat een op de vijf besturen in het mbo een onvoldoende krijgt voor de borging van kwaliteitszorg;</al>
            <al>overwegende dat echte emancipatie en kansengelijkheid voor mbo-studenten begint bij het bieden van goed onderwijs;</al>
            <al>verzoekt de regering om de komende periode prioriteit te maken van het verbeteren van de onderwijskwaliteit op het mbo,</al>
            <al>en gaat over tot de orde van de dag.</al>
            <al>Tseggai</al>
          </tekst>
        </vrije-tekst>
      </algemeen>
    </stuk>
  </kamerstuk>
</officiele-publicatie>