{
  "content": "Vergaderjaar 2023-2024\nTweede Kamer der Staten-Generaal\n2\nKamerstukken\n31 066\nBelastingdienst\nNr.\n1407\nMOTIE VAN HET LID KAMMINGA C.S.\nVoorgesteld\n13 juni 2024\nDe Kamer,\ngehoord de beraadslaging,\nconstaterende dat het kabinet voornemens is om de schaderoute via de Stichting (Gelijk)waardig Herstel en andere routes voort te zetten;\noverwegende dat het van belang is om ontwikkelingen binnen de herstelopgave goed te monitoren om waar nodig te kunnen bijsturen en zo ook op lange termijn de zorgvuldigheid en uitlegbaarheid van de verschillende routes te kunnen waarborgen en de lessons learned een plek te kunnen geven;\nverzoekt de regering om een evaluatieplan op te stellen en dit nog komend najaar aan de Kamer te doen toekomen, inclusief mogelijkheden voor versnelling,\nen gaat over tot de orde van de dag.\nKamminga\nOmtzigt\nFlach\nVermeer",
  "content_char_count": 842,
  "source": {
    "document_id": "5a338118-2491-4a56-a27b-0f22ebcdf281",
    "document_nummer": "2024D24771",
    "document_soort": "Motie",
    "publication_id": "635bb464-c533-46a4-a4c4-c473705b4485",
    "publication_content_type": "application/xml",
    "publication_length": 2292,
    "cached": false,
    "binary_path": "bronmateriaal-onbewerkt\\cache\\document_publications\\635bb464-c533-46a4-a4c4-c473705b4485.xml"
  },
  "issues": []
}