{
  "@odata.context": "https://gegevensmagazijn.tweedekamer.nl/OData/v4/2.0/$metadata#Stemming(Besluit(Agendapunt(Zaak())),Fractie(),Persoon())",
  "value": [
    {
      "Id": "1ad10620-ad19-4608-b5d4-0efc00331b3c",
      "Besluit_Id": "b161b247-4b7a-4846-92c8-9a0abcd9cd44",
      "Soort": "Tegen",
      "FractieGrootte": 25,
      "ActorNaam": "GroenLinks-PvdA",
      "ActorFractie": "GroenLinks-PvdA",
      "Vergissing": false,
      "SidActorLid": null,
      "SidActorFractie": "S-1-365867521-2120874753-4073584695-1095381795-2473312939-1823855426",
      "Persoon_Id": null,
      "Fractie_Id": "0208097d-ef04-438a-8c29-eebb84956204",
      "GewijzigdOp": "2025-07-04T11:25:05.38+02:00",
      "ApiGewijzigdOp": "2025-07-04T09:25:08.9970565Z",
      "Verwijderd": false,
      "Besluit": {
        "Id": "b161b247-4b7a-4846-92c8-9a0abcd9cd44",
        "Agendapunt_Id": "83169fde-dc45-45f7-9c68-ffbfaea54936",
        "StemmingsSoort": "Met handopsteken",
        "BesluitSoort": "Stemmen - verworpen",
        "BesluitTekst": "Verworpen.",
        "Opmerking": null,
        "Status": "Besluit",
        "AgendapuntZaakBesluitVolgorde": 10,
        "GewijzigdOp": "2025-07-04T00:20:11.5+02:00",
        "ApiGewijzigdOp": "2025-07-03T22:20:16.4386265Z",
        "Verwijderd": false,
        "Agendapunt": {
          "Id": "83169fde-dc45-45f7-9c68-ffbfaea54936",
          "Nummer": "2025P13110",
          "Onderwerp": "Stemmingen over: moties ingediend bij het debat over kritiek op het onderzoek van de jeugdbescherming naar de eigen rol bij de toeslagenaffaire",
          "Aanvangstijd": null,
          "Eindtijd": null,
          "Volgorde": 13,
          "Rubriek": null,
          "Noot": null,
          "Status": "Vrijgegeven",
          "GewijzigdOp": "2025-07-03T20:42:16.107+02:00",
          "ApiGewijzigdOp": "2025-07-03T18:42:20.7554089Z",
          "Verwijderd": false,
          "Activiteit_Id": "6266b2a3-30c7-4fd7-bc81-145a3ef7c783",
          "Zaak": [
            {
              "Id": "09b56176-2205-4001-b67b-015cdfea30fe",
              "Nummer": "2025Z14190",
              "Soort": "Motie",
              "Titel": "Toeslagen",
              "Citeertitel": null,
              "Alias": null,
              "Status": "Vrijgegeven",
              "Onderwerp": "Motie van het lid Bruyning over binnen de jeugdbeschermingsketen een systemische en relationele benadering bevorderen waarin gezin, netwerk en herstel centraal staan",
              "GestartOp": "2025-07-03T00:00:00+02:00",
              "Organisatie": "Tweede Kamer",
              "Grondslagvoorhang": null,
              "Termijn": null,
              "Vergaderjaar": "2024-2025",
              "Volgnummer": 32,
              "HuidigeBehandelstatus": null,
              "Afgedaan": true,
              "GrootProject": false,
              "GewijzigdOp": "2025-07-04T00:22:01.617+02:00",
              "ApiGewijzigdOp": "2025-07-30T13:23:43.654163Z",
              "Verwijderd": false,
              "Kabinetsappreciatie": "Oordeel Kamer"
            },
            {
              "Id": "806bdf2d-63a0-46fd-887a-1453f3d63457",
              "Nummer": "2025Z14188",
              "Soort": "Motie",
              "Titel": "Toeslagen",
              "Citeertitel": null,
              "Alias": null,
              "Status": "Vrijgegeven",
              "Onderwerp": "Motie van het lid Ceder c.s. over instellen van een staatscommissie die onderzoek doet naar uithuisplaatsingen",
              "GestartOp": "2025-07-03T00:00:00+02:00",
              "Organisatie": "Tweede Kamer",
              "Grondslagvoorhang": null,
              "Termijn": null,
              "Vergaderjaar": "2024-2025",
              "Volgnummer": 30,
              "HuidigeBehandelstatus": null,
              "Afgedaan": true,
              "GrootProject": false,
              "GewijzigdOp": "2025-07-04T00:18:11.283+02:00",
              "ApiGewijzigdOp": "2025-07-08T08:05:07.9970551Z",
              "Verwijderd": false,
              "Kabinetsappreciatie": "Oordeel Kamer"
            },
            {
              "Id": "f2cc6907-af80-48bc-9675-192c9de4e29f",
              "Nummer": "2025Z14189",
              "Soort": "Motie",
              "Titel": "Toeslagen",
              "Citeertitel": null,
              "Alias": null,
              "Status": "Vrijgegeven",
              "Onderwerp": "Motie van het lid Bruyning over zich actief inzetten voor herstel voor ouders en kinderen die zijn geraakt door de toeslagenaffaire en uithuisplaatsingen",
              "GestartOp": "2025-07-03T00:00:00+02:00",
              "Organisatie": "Tweede Kamer",
              "Grondslagvoorhang": null,
              "Termijn": null,
              "Vergaderjaar": "2024-2025",
              "Volgnummer": 31,
              "HuidigeBehandelstatus": null,
              "Afgedaan": true,
              "GrootProject": false,
              "GewijzigdOp": "2025-07-04T00:22:01.617+02:00",
              "ApiGewijzigdOp": "2025-07-08T08:05:20.5666123Z",
              "Verwijderd": false,
              "Kabinetsappreciatie": "Oordeel Kamer"
            },
            {
              "Id": "20620d43-33cd-4e02-b4a4-1c3174aa5dd8",
              "Nummer": "2025Z14196",
              "Soort": "Motie",
              "Titel": "Toeslagen",
              "Citeertitel": null,
              "Alias": null,
              "Status": "Vrijgegeven",
              "Onderwerp": "Motie van het lid Crijns over verbieden dat organisaties die betrokken zijn bij ernstige misstanden in de toekomst nog zelfevaluaties uitvoeren zonder onafhankelijke externe toetsing of regie",
              "GestartOp": "2025-07-03T00:00:00+02:00",
              "Organisatie": "Tweede Kamer",
              "Grondslagvoorhang": null,
              "Termijn": null,
              "Vergaderjaar": "2024-2025",
              "Volgnummer": 38,
              "HuidigeBehandelstatus": null,
              "Afgedaan": true,
              "GrootProject": false,
              "GewijzigdOp": "2025-07-04T00:20:11.503+02:00",
              "ApiGewijzigdOp": "2025-07-08T08:05:30.7593368Z",
              "Verwijderd": false,
              "Kabinetsappreciatie": "Ontraden"
            },
            {
              "Id": "048a36e2-e687-4f32-9ca7-2eef58e13613",
              "Nummer": "2025Z14191",
              "Soort": "Motie",
              "Titel": "Toeslagen",
              "Citeertitel": null,
              "Alias": null,
              "Status": "Vrijgegeven",
              "Onderwerp": "Motie van het lid Inge van Dijk c.s. over een plan voor verbetering van de kindregeling die recht doet aan de behoefte van kinderen",
              "GestartOp": "2025-07-03T00:00:00+02:00",
              "Organisatie": "Tweede Kamer",
              "Grondslagvoorhang": null,
              "Termijn": null,
              "Vergaderjaar": "2024-2025",
              "Volgnummer": 33,
              "HuidigeBehandelstatus": null,
              "Afgedaan": true,
              "GrootProject": false,
              "GewijzigdOp": "2025-07-04T00:22:01.62+02:00",
              "ApiGewijzigdOp": "2025-07-08T08:05:20.580859Z",
              "Verwijderd": false,
              "Kabinetsappreciatie": "Oordeel Kamer"
            },
            {
              "Id": "bc26678f-772a-43eb-941f-321611a3f64f",
              "Nummer": "2025Z14194",
              "Soort": "Motie",
              "Titel": "Toeslagen",
              "Citeertitel": null,
              "Alias": null,
              "Status": "Vrijgegeven",
              "Onderwerp": "Motie van het lid Dijk over in kaart brengen hoeveel jongeren getroffen door het toeslagenschandaal een schuld bij DUO hebben ",
              "GestartOp": "2025-07-03T00:00:00+02:00",
              "Organisatie": "Tweede Kamer",
              "Grondslagvoorhang": null,
              "Termijn": null,
              "Vergaderjaar": "2024-2025",
              "Volgnummer": 36,
              "HuidigeBehandelstatus": null,
              "Afgedaan": true,
              "GrootProject": false,
              "GewijzigdOp": "2025-07-04T00:22:26.67+02:00",
              "ApiGewijzigdOp": "2025-07-08T08:05:30.7348034Z",
              "Verwijderd": false,
              "Kabinetsappreciatie": "Ontraden"
            },
            {
              "Id": "691bae2d-9fe9-45ec-b2c6-512a6667df18",
              "Nummer": "2025Z14195",
              "Soort": "Motie",
              "Titel": "Toeslagen",
              "Citeertitel": null,
              "Alias": null,
              "Status": "Vrijgegeven",
              "Onderwerp": "Motie van het lid Crijns over zorgen dat bestuurders die ernstig falen worden gedwongen tot aftreden en dat jeugdbeschermers die hun plicht ernstig verzaken worden ontslagen",
              "GestartOp": "2025-07-03T00:00:00+02:00",
              "Organisatie": "Tweede Kamer",
              "Grondslagvoorhang": null,
              "Termijn": null,
              "Vergaderjaar": "2024-2025",
              "Volgnummer": 37,
              "HuidigeBehandelstatus": null,
              "Afgedaan": true,
              "GrootProject": false,
              "GewijzigdOp": "2025-07-04T00:22:26.67+02:00",
              "ApiGewijzigdOp": "2025-07-08T08:05:30.7470143Z",
              "Verwijderd": false,
              "Kabinetsappreciatie": "Ontraden"
            },
            {
              "Id": "5d981dda-2ae5-4ad9-a373-5b74a3273993",
              "Nummer": "2025Z14187",
              "Soort": "Motie",
              "Titel": "Toeslagen",
              "Citeertitel": null,
              "Alias": null,
              "Status": "Vrijgegeven",
              "Onderwerp": "Motie van de leden Ceder en Bruyning over wettelijk verankeren dat terugplaatsing naar huis het uitgangspunt is bij uithuisplaatsingen",
              "GestartOp": "2025-07-03T00:00:00+02:00",
              "Organisatie": "Tweede Kamer",
              "Grondslagvoorhang": null,
              "Termijn": null,
              "Vergaderjaar": "2024-2025",
              "Volgnummer": 29,
              "HuidigeBehandelstatus": null,
              "Afgedaan": true,
              "GrootProject": false,
              "GewijzigdOp": "2025-07-04T00:18:11.283+02:00",
              "ApiGewijzigdOp": "2025-07-08T08:05:04.8660488Z",
              "Verwijderd": false,
              "Kabinetsappreciatie": "Oordeel Kamer"
            },
            {
              "Id": "185d08a6-8d5c-4b3b-b6ae-7dc65d48b861",
              "Nummer": "2025Z14192",
              "Soort": "Motie",
              "Titel": "Toeslagen",
              "Citeertitel": null,
              "Alias": null,
              "Status": "Vrijgegeven",
              "Onderwerp": "Motie van het lid Westerveld over een tijdlijn met duidelijke deadlines en een concrete uitwerking van de ondersteuningsmaatregelen inclusief financiële dekking ",
              "GestartOp": "2025-07-03T00:00:00+02:00",
              "Organisatie": "Tweede Kamer",
              "Grondslagvoorhang": null,
              "Termijn": null,
              "Vergaderjaar": "2024-2025",
              "Volgnummer": 34,
              "HuidigeBehandelstatus": null,
              "Afgedaan": true,
              "GrootProject": false,
              "GewijzigdOp": "2025-07-04T00:22:01.62+02:00",
              "ApiGewijzigdOp": "2025-07-08T08:03:27.9122114Z",
              "Verwijderd": false,
              "Kabinetsappreciatie": "Oordeel Kamer"
            },
            {
              "Id": "edf9b224-f388-445d-947e-9bf419345a60",
              "Nummer": "2025Z14197",
              "Soort": "Motie",
              "Titel": "Toeslagen",
              "Citeertitel": null,
              "Alias": null,
              "Status": "Vrijgegeven",
              "Onderwerp": "Motie van het lid El Abassi over uitspreken dat pas recht gedaan kan worden aan het leed van gedupeerde gezinnen als alle betrokken ketenpartners openlijk verantwoordelijkheid nemen voor hun rol in de toeslagenaffaire",
              "GestartOp": "2025-07-03T00:00:00+02:00",
              "Organisatie": "Tweede Kamer",
              "Grondslagvoorhang": null,
              "Termijn": null,
              "Vergaderjaar": "2024-2025",
              "Volgnummer": 39,
              "HuidigeBehandelstatus": null,
              "Afgedaan": true,
              "GrootProject": false,
              "GewijzigdOp": "2025-07-04T00:20:11.507+02:00",
              "ApiGewijzigdOp": "2025-07-08T08:11:32.0215713Z",
              "Verwijderd": false,
              "Kabinetsappreciatie": "Geen (expliciete) appreciatie"
            },
            {
              "Id": "27c431c2-7bfb-42d1-92f5-a666cc41dc72",
              "Nummer": "2025Z14193",
              "Soort": "Motie",
              "Titel": "Toeslagen",
              "Citeertitel": null,
              "Alias": null,
              "Status": "Vrijgegeven",
              "Onderwerp": "Motie van het lid Dijk over het kwijtschelden van DUO-schulden van gedupeerde jongeren die zijn gebruikt om hun ouders te helpen",
              "GestartOp": "2025-07-03T00:00:00+02:00",
              "Organisatie": "Tweede Kamer",
              "Grondslagvoorhang": null,
              "Termijn": null,
              "Vergaderjaar": "2024-2025",
              "Volgnummer": 35,
              "HuidigeBehandelstatus": null,
              "Afgedaan": true,
              "GrootProject": false,
              "GewijzigdOp": "2025-07-04T00:22:26.667+02:00",
              "ApiGewijzigdOp": "2025-07-08T08:05:21.6774175Z",
              "Verwijderd": false,
              "Kabinetsappreciatie": "Ontraden"
            },
            {
              "Id": "1c60ed97-30a9-4d0b-93ce-d0080fe1d7f3",
              "Nummer": "2025Z14198",
              "Soort": "Motie",
              "Titel": "Toeslagen",
              "Citeertitel": null,
              "Alias": null,
              "Status": "Vrijgegeven",
              "Onderwerp": "Motie van het lid El Abassi over uitspreken dat gedupeerde gezinnen recht hebben op volledig herstel",
              "GestartOp": "2025-07-03T00:00:00+02:00",
              "Organisatie": "Tweede Kamer",
              "Grondslagvoorhang": null,
              "Termijn": null,
              "Vergaderjaar": "2024-2025",
              "Volgnummer": 40,
              "HuidigeBehandelstatus": null,
              "Afgedaan": true,
              "GrootProject": false,
              "GewijzigdOp": "2025-07-04T00:20:21.5+02:00",
              "ApiGewijzigdOp": "2025-07-08T08:12:02.8146857Z",
              "Verwijderd": false,
              "Kabinetsappreciatie": "Geen (expliciete) appreciatie"
            }
          ]
        }
      },
      "Fractie": {
        "Id": "0208097d-ef04-438a-8c29-eebb84956204",
        "Nummer": 58395,
        "Afkorting": "GroenLinks-PvdA",
        "NaamNL": "GroenLinks-PvdA",
        "NaamEN": "Green Left-Labour Party",
        "AantalZetels": 25,
        "AantalStemmen": 1643073,
        "DatumActief": "2023-10-27T00:00:00+02:00",
        "DatumInactief": null,
        "ContentType": "image/jpeg",
        "ContentLength": 40180,
        "GewijzigdOp": "2025-02-28T10:46:16.4063869+01:00",
        "ApiGewijzigdOp": "2025-02-28T09:47:10.9064301Z",
        "Verwijderd": false
      },
      "Persoon": null
    },
    {
      "Id": "99fa8d5d-9090-4a31-8b57-086857e20e75",
      "Besluit_Id": "f3dabffe-40f6-437b-bec1-d4cc170892ea",
      "Soort": "Tegen",
      "FractieGrootte": 37,
      "ActorNaam": "PVV",
      "ActorFractie": "PVV",
      "Vergissing": false,
      "SidActorLid": null,
      "SidActorFractie": "S-1-365867521-2120874753-203711267-1259409971-1122177929-1764465637",
      "Persoon_Id": null,
      "Fractie_Id": "65129918-f256-4975-9da4-488da34d6695",
      "GewijzigdOp": "2025-07-04T11:25:30.447+02:00",
      "ApiGewijzigdOp": "2025-07-04T09:25:36.8720246Z",
      "Verwijderd": false,
      "Besluit": {
        "Id": "f3dabffe-40f6-437b-bec1-d4cc170892ea",
        "Agendapunt_Id": "83169fde-dc45-45f7-9c68-ffbfaea54936",
        "StemmingsSoort": "Met handopsteken",
        "BesluitSoort": "Stemmen - verworpen",
        "BesluitTekst": "Verworpen.",
        "Opmerking": null,
        "Status": "Besluit",
        "AgendapuntZaakBesluitVolgorde": 11,
        "GewijzigdOp": "2025-07-04T00:20:11.503+02:00",
        "ApiGewijzigdOp": "2025-07-03T22:20:16.4646906Z",
        "Verwijderd": false,
        "Agendapunt": {
          "Id": "83169fde-dc45-45f7-9c68-ffbfaea54936",
          "Nummer": "2025P13110",
          "Onderwerp": "Stemmingen over: moties ingediend bij het debat over kritiek op het onderzoek van de jeugdbescherming naar de eigen rol bij de toeslagenaffaire",
          "Aanvangstijd": null,
          "Eindtijd": null,
          "Volgorde": 13,
          "Rubriek": null,
          "Noot": null,
          "Status": "Vrijgegeven",
          "GewijzigdOp": "2025-07-03T20:42:16.107+02:00",
          "ApiGewijzigdOp": "2025-07-03T18:42:20.7554089Z",
          "Verwijderd": false,
          "Activiteit_Id": "6266b2a3-30c7-4fd7-bc81-145a3ef7c783",
          "Zaak": [
            {
              "Id": "09b56176-2205-4001-b67b-015cdfea30fe",
              "Nummer": "2025Z14190",
              "Soort": "Motie",
              "Titel": "Toeslagen",
              "Citeertitel": null,
              "Alias": null,
              "Status": "Vrijgegeven",
              "Onderwerp": "Motie van het lid Bruyning over binnen de jeugdbeschermingsketen een systemische en relationele benadering bevorderen waarin gezin, netwerk en herstel centraal staan",
              "GestartOp": "2025-07-03T00:00:00+02:00",
              "Organisatie": "Tweede Kamer",
              "Grondslagvoorhang": null,
              "Termijn": null,
              "Vergaderjaar": "2024-2025",
              "Volgnummer": 32,
              "HuidigeBehandelstatus": null,
              "Afgedaan": true,
              "GrootProject": false,
              "GewijzigdOp": "2025-07-04T00:22:01.617+02:00",
              "ApiGewijzigdOp": "2025-07-30T13:23:43.654163Z",
              "Verwijderd": false,
              "Kabinetsappreciatie": "Oordeel Kamer"
            },
            {
              "Id": "806bdf2d-63a0-46fd-887a-1453f3d63457",
              "Nummer": "2025Z14188",
              "Soort": "Motie",
              "Titel": "Toeslagen",
              "Citeertitel": null,
              "Alias": null,
              "Status": "Vrijgegeven",
              "Onderwerp": "Motie van het lid Ceder c.s. over instellen van een staatscommissie die onderzoek doet naar uithuisplaatsingen",
              "GestartOp": "2025-07-03T00:00:00+02:00",
              "Organisatie": "Tweede Kamer",
              "Grondslagvoorhang": null,
              "Termijn": null,
              "Vergaderjaar": "2024-2025",
              "Volgnummer": 30,
              "HuidigeBehandelstatus": null,
              "Afgedaan": true,
              "GrootProject": false,
              "GewijzigdOp": "2025-07-04T00:18:11.283+02:00",
              "ApiGewijzigdOp": "2025-07-08T08:05:07.9970551Z",
              "Verwijderd": false,
              "Kabinetsappreciatie": "Oordeel Kamer"
            },
            {
              "Id": "f2cc6907-af80-48bc-9675-192c9de4e29f",
              "Nummer": "2025Z14189",
              "Soort": "Motie",
              "Titel": "Toeslagen",
              "Citeertitel": null,
              "Alias": null,
              "Status": "Vrijgegeven",
              "Onderwerp": "Motie van het lid Bruyning over zich actief inzetten voor herstel voor ouders en kinderen die zijn geraakt door de toeslagenaffaire en uithuisplaatsingen",
              "GestartOp": "2025-07-03T00:00:00+02:00",
              "Organisatie": "Tweede Kamer",
              "Grondslagvoorhang": null,
              "Termijn": null,
              "Vergaderjaar": "2024-2025",
              "Volgnummer": 31,
              "HuidigeBehandelstatus": null,
              "Afgedaan": true,
              "GrootProject": false,
              "GewijzigdOp": "2025-07-04T00:22:01.617+02:00",
              "ApiGewijzigdOp": "2025-07-08T08:05:20.5666123Z",
              "Verwijderd": false,
              "Kabinetsappreciatie": "Oordeel Kamer"
            },
            {
              "Id": "20620d43-33cd-4e02-b4a4-1c3174aa5dd8",
              "Nummer": "2025Z14196",
              "Soort": "Motie",
              "Titel": "Toeslagen",
              "Citeertitel": null,
              "Alias": null,
              "Status": "Vrijgegeven",
              "Onderwerp": "Motie van het lid Crijns over verbieden dat organisaties die betrokken zijn bij ernstige misstanden in de toekomst nog zelfevaluaties uitvoeren zonder onafhankelijke externe toetsing of regie",
              "GestartOp": "2025-07-03T00:00:00+02:00",
              "Organisatie": "Tweede Kamer",
              "Grondslagvoorhang": null,
              "Termijn": null,
              "Vergaderjaar": "2024-2025",
              "Volgnummer": 38,
              "HuidigeBehandelstatus": null,
              "Afgedaan": true,
              "GrootProject": false,
              "GewijzigdOp": "2025-07-04T00:20:11.503+02:00",
              "ApiGewijzigdOp": "2025-07-08T08:05:30.7593368Z",
              "Verwijderd": false,
              "Kabinetsappreciatie": "Ontraden"
            },
            {
              "Id": "048a36e2-e687-4f32-9ca7-2eef58e13613",
              "Nummer": "2025Z14191",
              "Soort": "Motie",
              "Titel": "Toeslagen",
              "Citeertitel": null,
              "Alias": null,
              "Status": "Vrijgegeven",
              "Onderwerp": "Motie van het lid Inge van Dijk c.s. over een plan voor verbetering van de kindregeling die recht doet aan de behoefte van kinderen",
              "GestartOp": "2025-07-03T00:00:00+02:00",
              "Organisatie": "Tweede Kamer",
              "Grondslagvoorhang": null,
              "Termijn": null,
              "Vergaderjaar": "2024-2025",
              "Volgnummer": 33,
              "HuidigeBehandelstatus": null,
              "Afgedaan": true,
              "GrootProject": false,
              "GewijzigdOp": "2025-07-04T00:22:01.62+02:00",
              "ApiGewijzigdOp": "2025-07-08T08:05:20.580859Z",
              "Verwijderd": false,
              "Kabinetsappreciatie": "Oordeel Kamer"
            },
            {
              "Id": "bc26678f-772a-43eb-941f-321611a3f64f",
              "Nummer": "2025Z14194",
              "Soort": "Motie",
              "Titel": "Toeslagen",
              "Citeertitel": null,
              "Alias": null,
              "Status": "Vrijgegeven",
              "Onderwerp": "Motie van het lid Dijk over in kaart brengen hoeveel jongeren getroffen door het toeslagenschandaal een schuld bij DUO hebben ",
              "GestartOp": "2025-07-03T00:00:00+02:00",
              "Organisatie": "Tweede Kamer",
              "Grondslagvoorhang": null,
              "Termijn": null,
              "Vergaderjaar": "2024-2025",
              "Volgnummer": 36,
              "HuidigeBehandelstatus": null,
              "Afgedaan": true,
              "GrootProject": false,
              "GewijzigdOp": "2025-07-04T00:22:26.67+02:00",
              "ApiGewijzigdOp": "2025-07-08T08:05:30.7348034Z",
              "Verwijderd": false,
              "Kabinetsappreciatie": "Ontraden"
            },
            {
              "Id": "691bae2d-9fe9-45ec-b2c6-512a6667df18",
              "Nummer": "2025Z14195",
              "Soort": "Motie",
              "Titel": "Toeslagen",
              "Citeertitel": null,
              "Alias": null,
              "Status": "Vrijgegeven",
              "Onderwerp": "Motie van het lid Crijns over zorgen dat bestuurders die ernstig falen worden gedwongen tot aftreden en dat jeugdbeschermers die hun plicht ernstig verzaken worden ontslagen",
              "GestartOp": "2025-07-03T00:00:00+02:00",
              "Organisatie": "Tweede Kamer",
              "Grondslagvoorhang": null,
              "Termijn": null,
              "Vergaderjaar": "2024-2025",
              "Volgnummer": 37,
              "HuidigeBehandelstatus": null,
              "Afgedaan": true,
              "GrootProject": false,
              "GewijzigdOp": "2025-07-04T00:22:26.67+02:00",
              "ApiGewijzigdOp": "2025-07-08T08:05:30.7470143Z",
              "Verwijderd": false,
              "Kabinetsappreciatie": "Ontraden"
            },
            {
              "Id": "5d981dda-2ae5-4ad9-a373-5b74a3273993",
              "Nummer": "2025Z14187",
              "Soort": "Motie",
              "Titel": "Toeslagen",
              "Citeertitel": null,
              "Alias": null,
              "Status": "Vrijgegeven",
              "Onderwerp": "Motie van de leden Ceder en Bruyning over wettelijk verankeren dat terugplaatsing naar huis het uitgangspunt is bij uithuisplaatsingen",
              "GestartOp": "2025-07-03T00:00:00+02:00",
              "Organisatie": "Tweede Kamer",
              "Grondslagvoorhang": null,
              "Termijn": null,
              "Vergaderjaar": "2024-2025",
              "Volgnummer": 29,
              "HuidigeBehandelstatus": null,
              "Afgedaan": true,
              "GrootProject": false,
              "GewijzigdOp": "2025-07-04T00:18:11.283+02:00",
              "ApiGewijzigdOp": "2025-07-08T08:05:04.8660488Z",
              "Verwijderd": false,
              "Kabinetsappreciatie": "Oordeel Kamer"
            },
            {
              "Id": "185d08a6-8d5c-4b3b-b6ae-7dc65d48b861",
              "Nummer": "2025Z14192",
              "Soort": "Motie",
              "Titel": "Toeslagen",
              "Citeertitel": null,
              "Alias": null,
              "Status": "Vrijgegeven",
              "Onderwerp": "Motie van het lid Westerveld over een tijdlijn met duidelijke deadlines en een concrete uitwerking van de ondersteuningsmaatregelen inclusief financiële dekking ",
              "GestartOp": "2025-07-03T00:00:00+02:00",
              "Organisatie": "Tweede Kamer",
              "Grondslagvoorhang": null,
              "Termijn": null,
              "Vergaderjaar": "2024-2025",
              "Volgnummer": 34,
              "HuidigeBehandelstatus": null,
              "Afgedaan": true,
              "GrootProject": false,
              "GewijzigdOp": "2025-07-04T00:22:01.62+02:00",
              "ApiGewijzigdOp": "2025-07-08T08:03:27.9122114Z",
              "Verwijderd": false,
              "Kabinetsappreciatie": "Oordeel Kamer"
            },
            {
              "Id": "edf9b224-f388-445d-947e-9bf419345a60",
              "Nummer": "2025Z14197",
              "Soort": "Motie",
              "Titel": "Toeslagen",
              "Citeertitel": null,
              "Alias": null,
              "Status": "Vrijgegeven",
              "Onderwerp": "Motie van het lid El Abassi over uitspreken dat pas recht gedaan kan worden aan het leed van gedupeerde gezinnen als alle betrokken ketenpartners openlijk verantwoordelijkheid nemen voor hun rol in de toeslagenaffaire",
              "GestartOp": "2025-07-03T00:00:00+02:00",
              "Organisatie": "Tweede Kamer",
              "Grondslagvoorhang": null,
              "Termijn": null,
              "Vergaderjaar": "2024-2025",
              "Volgnummer": 39,
              "HuidigeBehandelstatus": null,
              "Afgedaan": true,
              "GrootProject": false,
              "GewijzigdOp": "2025-07-04T00:20:11.507+02:00",
              "ApiGewijzigdOp": "2025-07-08T08:11:32.0215713Z",
              "Verwijderd": false,
              "Kabinetsappreciatie": "Geen (expliciete) appreciatie"
            },
            {
              "Id": "27c431c2-7bfb-42d1-92f5-a666cc41dc72",
              "Nummer": "2025Z14193",
              "Soort": "Motie",
              "Titel": "Toeslagen",
              "Citeertitel": null,
              "Alias": null,
              "Status": "Vrijgegeven",
              "Onderwerp": "Motie van het lid Dijk over het kwijtschelden van DUO-schulden van gedupeerde jongeren die zijn gebruikt om hun ouders te helpen",
              "GestartOp": "2025-07-03T00:00:00+02:00",
              "Organisatie": "Tweede Kamer",
              "Grondslagvoorhang": null,
              "Termijn": null,
              "Vergaderjaar": "2024-2025",
              "Volgnummer": 35,
              "HuidigeBehandelstatus": null,
              "Afgedaan": true,
              "GrootProject": false,
              "GewijzigdOp": "2025-07-04T00:22:26.667+02:00",
              "ApiGewijzigdOp": "2025-07-08T08:05:21.6774175Z",
              "Verwijderd": false,
              "Kabinetsappreciatie": "Ontraden"
            },
            {
              "Id": "1c60ed97-30a9-4d0b-93ce-d0080fe1d7f3",
              "Nummer": "2025Z14198",
              "Soort": "Motie",
              "Titel": "Toeslagen",
              "Citeertitel": null,
              "Alias": null,
              "Status": "Vrijgegeven",
              "Onderwerp": "Motie van het lid El Abassi over uitspreken dat gedupeerde gezinnen recht hebben op volledig herstel",
              "GestartOp": "2025-07-03T00:00:00+02:00",
              "Organisatie": "Tweede Kamer",
              "Grondslagvoorhang": null,
              "Termijn": null,
              "Vergaderjaar": "2024-2025",
              "Volgnummer": 40,
              "HuidigeBehandelstatus": null,
              "Afgedaan": true,
              "GrootProject": false,
              "GewijzigdOp": "2025-07-04T00:20:21.5+02:00",
              "ApiGewijzigdOp": "2025-07-08T08:12:02.8146857Z",
              "Verwijderd": false,
              "Kabinetsappreciatie": "Geen (expliciete) appreciatie"
            }
          ]
        }
      },
      "Fractie": {
        "Id": "65129918-f256-4975-9da4-488da34d6695",
        "Nummer": 2765,
        "Afkorting": "PVV",
        "NaamNL": "Partij voor de Vrijheid",
        "NaamEN": "Party for Freedom",
        "AantalZetels": 37,
        "AantalStemmen": 2450878,
        "DatumActief": "2006-11-30T00:00:00+01:00",
        "DatumInactief": null,
        "ContentType": "image/jpeg",
        "ContentLength": 4484,
        "GewijzigdOp": "2025-02-12T11:27:01+01:00",
        "ApiGewijzigdOp": "2025-02-12T10:28:11.8804659Z",
        "Verwijderd": false
      },
      "Persoon": null
    },
    {
      "Id": "15a970ec-b3fb-466e-9e5d-06a267834681",
      "Besluit_Id": "ec22d1f1-10c6-4e82-bb8a-e9ef7ea3424e",
      "Soort": "Voor",
      "FractieGrootte": 5,
      "ActorNaam": "SP",
      "ActorFractie": "SP",
      "Vergissing": false,
      "SidActorLid": null,
      "SidActorFractie": "S-1-365867521-2120874753-3918075670-1133036099-4208265915-4115381510",
      "Persoon_Id": null,
      "Fractie_Id": "a3689bb6-3914-4d5c-a6a8-42e24582e299",
      "GewijzigdOp": "2025-07-04T11:26:10.473+02:00",
      "ApiGewijzigdOp": "2025-07-04T09:26:16.450786Z",
      "Verwijderd": false,
      "Besluit": {
        "Id": "ec22d1f1-10c6-4e82-bb8a-e9ef7ea3424e",
        "Agendapunt_Id": "83169fde-dc45-45f7-9c68-ffbfaea54936",
        "StemmingsSoort": "Met handopsteken",
        "BesluitSoort": "Stemmen - aangenomen",
        "BesluitTekst": "Aangenomen.",
        "Opmerking": null,
        "Status": "Besluit",
        "AgendapuntZaakBesluitVolgorde": 12,
        "GewijzigdOp": "2025-07-04T00:20:21.497+02:00",
        "ApiGewijzigdOp": "2025-07-03T22:20:24.7905661Z",
        "Verwijderd": false,
        "Agendapunt": {
          "Id": "83169fde-dc45-45f7-9c68-ffbfaea54936",
          "Nummer": "2025P13110",
          "Onderwerp": "Stemmingen over: moties ingediend bij het debat over kritiek op het onderzoek van de jeugdbescherming naar de eigen rol bij de toeslagenaffaire",
          "Aanvangstijd": null,
          "Eindtijd": null,
          "Volgorde": 13,
          "Rubriek": null,
          "Noot": null,
          "Status": "Vrijgegeven",
          "GewijzigdOp": "2025-07-03T20:42:16.107+02:00",
          "ApiGewijzigdOp": "2025-07-03T18:42:20.7554089Z",
          "Verwijderd": false,
          "Activiteit_Id": "6266b2a3-30c7-4fd7-bc81-145a3ef7c783",
          "Zaak": [
            {
              "Id": "09b56176-2205-4001-b67b-015cdfea30fe",
              "Nummer": "2025Z14190",
              "Soort": "Motie",
              "Titel": "Toeslagen",
              "Citeertitel": null,
              "Alias": null,
              "Status": "Vrijgegeven",
              "Onderwerp": "Motie van het lid Bruyning over binnen de jeugdbeschermingsketen een systemische en relationele benadering bevorderen waarin gezin, netwerk en herstel centraal staan",
              "GestartOp": "2025-07-03T00:00:00+02:00",
              "Organisatie": "Tweede Kamer",
              "Grondslagvoorhang": null,
              "Termijn": null,
              "Vergaderjaar": "2024-2025",
              "Volgnummer": 32,
              "HuidigeBehandelstatus": null,
              "Afgedaan": true,
              "GrootProject": false,
              "GewijzigdOp": "2025-07-04T00:22:01.617+02:00",
              "ApiGewijzigdOp": "2025-07-30T13:23:43.654163Z",
              "Verwijderd": false,
              "Kabinetsappreciatie": "Oordeel Kamer"
            },
            {
              "Id": "806bdf2d-63a0-46fd-887a-1453f3d63457",
              "Nummer": "2025Z14188",
              "Soort": "Motie",
              "Titel": "Toeslagen",
              "Citeertitel": null,
              "Alias": null,
              "Status": "Vrijgegeven",
              "Onderwerp": "Motie van het lid Ceder c.s. over instellen van een staatscommissie die onderzoek doet naar uithuisplaatsingen",
              "GestartOp": "2025-07-03T00:00:00+02:00",
              "Organisatie": "Tweede Kamer",
              "Grondslagvoorhang": null,
              "Termijn": null,
              "Vergaderjaar": "2024-2025",
              "Volgnummer": 30,
              "HuidigeBehandelstatus": null,
              "Afgedaan": true,
              "GrootProject": false,
              "GewijzigdOp": "2025-07-04T00:18:11.283+02:00",
              "ApiGewijzigdOp": "2025-07-08T08:05:07.9970551Z",
              "Verwijderd": false,
              "Kabinetsappreciatie": "Oordeel Kamer"
            },
            {
              "Id": "f2cc6907-af80-48bc-9675-192c9de4e29f",
              "Nummer": "2025Z14189",
              "Soort": "Motie",
              "Titel": "Toeslagen",
              "Citeertitel": null,
              "Alias": null,
              "Status": "Vrijgegeven",
              "Onderwerp": "Motie van het lid Bruyning over zich actief inzetten voor herstel voor ouders en kinderen die zijn geraakt door de toeslagenaffaire en uithuisplaatsingen",
              "GestartOp": "2025-07-03T00:00:00+02:00",
              "Organisatie": "Tweede Kamer",
              "Grondslagvoorhang": null,
              "Termijn": null,
              "Vergaderjaar": "2024-2025",
              "Volgnummer": 31,
              "HuidigeBehandelstatus": null,
              "Afgedaan": true,
              "GrootProject": false,
              "GewijzigdOp": "2025-07-04T00:22:01.617+02:00",
              "ApiGewijzigdOp": "2025-07-08T08:05:20.5666123Z",
              "Verwijderd": false,
              "Kabinetsappreciatie": "Oordeel Kamer"
            },
            {
              "Id": "20620d43-33cd-4e02-b4a4-1c3174aa5dd8",
              "Nummer": "2025Z14196",
              "Soort": "Motie",
              "Titel": "Toeslagen",
              "Citeertitel": null,
              "Alias": null,
              "Status": "Vrijgegeven",
              "Onderwerp": "Motie van het lid Crijns over verbieden dat organisaties die betrokken zijn bij ernstige misstanden in de toekomst nog zelfevaluaties uitvoeren zonder onafhankelijke externe toetsing of regie",
              "GestartOp": "2025-07-03T00:00:00+02:00",
              "Organisatie": "Tweede Kamer",
              "Grondslagvoorhang": null,
              "Termijn": null,
              "Vergaderjaar": "2024-2025",
              "Volgnummer": 38,
              "HuidigeBehandelstatus": null,
              "Afgedaan": true,
              "GrootProject": false,
              "GewijzigdOp": "2025-07-04T00:20:11.503+02:00",
              "ApiGewijzigdOp": "2025-07-08T08:05:30.7593368Z",
              "Verwijderd": false,
              "Kabinetsappreciatie": "Ontraden"
            },
            {
              "Id": "048a36e2-e687-4f32-9ca7-2eef58e13613",
              "Nummer": "2025Z14191",
              "Soort": "Motie",
              "Titel": "Toeslagen",
              "Citeertitel": null,
              "Alias": null,
              "Status": "Vrijgegeven",
              "Onderwerp": "Motie van het lid Inge van Dijk c.s. over een plan voor verbetering van de kindregeling die recht doet aan de behoefte van kinderen",
              "GestartOp": "2025-07-03T00:00:00+02:00",
              "Organisatie": "Tweede Kamer",
              "Grondslagvoorhang": null,
              "Termijn": null,
              "Vergaderjaar": "2024-2025",
              "Volgnummer": 33,
              "HuidigeBehandelstatus": null,
              "Afgedaan": true,
              "GrootProject": false,
              "GewijzigdOp": "2025-07-04T00:22:01.62+02:00",
              "ApiGewijzigdOp": "2025-07-08T08:05:20.580859Z",
              "Verwijderd": false,
              "Kabinetsappreciatie": "Oordeel Kamer"
            },
            {
              "Id": "bc26678f-772a-43eb-941f-321611a3f64f",
              "Nummer": "2025Z14194",
              "Soort": "Motie",
              "Titel": "Toeslagen",
              "Citeertitel": null,
              "Alias": null,
              "Status": "Vrijgegeven",
              "Onderwerp": "Motie van het lid Dijk over in kaart brengen hoeveel jongeren getroffen door het toeslagenschandaal een schuld bij DUO hebben ",
              "GestartOp": "2025-07-03T00:00:00+02:00",
              "Organisatie": "Tweede Kamer",
              "Grondslagvoorhang": null,
              "Termijn": null,
              "Vergaderjaar": "2024-2025",
              "Volgnummer": 36,
              "HuidigeBehandelstatus": null,
              "Afgedaan": true,
              "GrootProject": false,
              "GewijzigdOp": "2025-07-04T00:22:26.67+02:00",
              "ApiGewijzigdOp": "2025-07-08T08:05:30.7348034Z",
              "Verwijderd": false,
              "Kabinetsappreciatie": "Ontraden"
            },
            {
              "Id": "691bae2d-9fe9-45ec-b2c6-512a6667df18",
              "Nummer": "2025Z14195",
              "Soort": "Motie",
              "Titel": "Toeslagen",
              "Citeertitel": null,
              "Alias": null,
              "Status": "Vrijgegeven",
              "Onderwerp": "Motie van het lid Crijns over zorgen dat bestuurders die ernstig falen worden gedwongen tot aftreden en dat jeugdbeschermers die hun plicht ernstig verzaken worden ontslagen",
              "GestartOp": "2025-07-03T00:00:00+02:00",
              "Organisatie": "Tweede Kamer",
              "Grondslagvoorhang": null,
              "Termijn": null,
              "Vergaderjaar": "2024-2025",
              "Volgnummer": 37,
              "HuidigeBehandelstatus": null,
              "Afgedaan": true,
              "GrootProject": false,
              "GewijzigdOp": "2025-07-04T00:22:26.67+02:00",
              "ApiGewijzigdOp": "2025-07-08T08:05:30.7470143Z",
              "Verwijderd": false,
              "Kabinetsappreciatie": "Ontraden"
            },
            {
              "Id": "5d981dda-2ae5-4ad9-a373-5b74a3273993",
              "Nummer": "2025Z14187",
              "Soort": "Motie",
              "Titel": "Toeslagen",
              "Citeertitel": null,
              "Alias": null,
              "Status": "Vrijgegeven",
              "Onderwerp": "Motie van de leden Ceder en Bruyning over wettelijk verankeren dat terugplaatsing naar huis het uitgangspunt is bij uithuisplaatsingen",
              "GestartOp": "2025-07-03T00:00:00+02:00",
              "Organisatie": "Tweede Kamer",
              "Grondslagvoorhang": null,
              "Termijn": null,
              "Vergaderjaar": "2024-2025",
              "Volgnummer": 29,
              "HuidigeBehandelstatus": null,
              "Afgedaan": true,
              "GrootProject": false,
              "GewijzigdOp": "2025-07-04T00:18:11.283+02:00",
              "ApiGewijzigdOp": "2025-07-08T08:05:04.8660488Z",
              "Verwijderd": false,
              "Kabinetsappreciatie": "Oordeel Kamer"
            },
            {
              "Id": "185d08a6-8d5c-4b3b-b6ae-7dc65d48b861",
              "Nummer": "2025Z14192",
              "Soort": "Motie",
              "Titel": "Toeslagen",
              "Citeertitel": null,
              "Alias": null,
              "Status": "Vrijgegeven",
              "Onderwerp": "Motie van het lid Westerveld over een tijdlijn met duidelijke deadlines en een concrete uitwerking van de ondersteuningsmaatregelen inclusief financiële dekking ",
              "GestartOp": "2025-07-03T00:00:00+02:00",
              "Organisatie": "Tweede Kamer",
              "Grondslagvoorhang": null,
              "Termijn": null,
              "Vergaderjaar": "2024-2025",
              "Volgnummer": 34,
              "HuidigeBehandelstatus": null,
              "Afgedaan": true,
              "GrootProject": false,
              "GewijzigdOp": "2025-07-04T00:22:01.62+02:00",
              "ApiGewijzigdOp": "2025-07-08T08:03:27.9122114Z",
              "Verwijderd": false,
              "Kabinetsappreciatie": "Oordeel Kamer"
            },
            {
              "Id": "edf9b224-f388-445d-947e-9bf419345a60",
              "Nummer": "2025Z14197",
              "Soort": "Motie",
              "Titel": "Toeslagen",
              "Citeertitel": null,
              "Alias": null,
              "Status": "Vrijgegeven",
              "Onderwerp": "Motie van het lid El Abassi over uitspreken dat pas recht gedaan kan worden aan het leed van gedupeerde gezinnen als alle betrokken ketenpartners openlijk verantwoordelijkheid nemen voor hun rol in de toeslagenaffaire",
              "GestartOp": "2025-07-03T00:00:00+02:00",
              "Organisatie": "Tweede Kamer",
              "Grondslagvoorhang": null,
              "Termijn": null,
              "Vergaderjaar": "2024-2025",
              "Volgnummer": 39,
              "HuidigeBehandelstatus": null,
              "Afgedaan": true,
              "GrootProject": false,
              "GewijzigdOp": "2025-07-04T00:20:11.507+02:00",
              "ApiGewijzigdOp": "2025-07-08T08:11:32.0215713Z",
              "Verwijderd": false,
              "Kabinetsappreciatie": "Geen (expliciete) appreciatie"
            },
            {
              "Id": "27c431c2-7bfb-42d1-92f5-a666cc41dc72",
              "Nummer": "2025Z14193",
              "Soort": "Motie",
              "Titel": "Toeslagen",
              "Citeertitel": null,
              "Alias": null,
              "Status": "Vrijgegeven",
              "Onderwerp": "Motie van het lid Dijk over het kwijtschelden van DUO-schulden van gedupeerde jongeren die zijn gebruikt om hun ouders te helpen",
              "GestartOp": "2025-07-03T00:00:00+02:00",
              "Organisatie": "Tweede Kamer",
              "Grondslagvoorhang": null,
              "Termijn": null,
              "Vergaderjaar": "2024-2025",
              "Volgnummer": 35,
              "HuidigeBehandelstatus": null,
              "Afgedaan": true,
              "GrootProject": false,
              "GewijzigdOp": "2025-07-04T00:22:26.667+02:00",
              "ApiGewijzigdOp": "2025-07-08T08:05:21.6774175Z",
              "Verwijderd": false,
              "Kabinetsappreciatie": "Ontraden"
            },
            {
              "Id": "1c60ed97-30a9-4d0b-93ce-d0080fe1d7f3",
              "Nummer": "2025Z14198",
              "Soort": "Motie",
              "Titel": "Toeslagen",
              "Citeertitel": null,
              "Alias": null,
              "Status": "Vrijgegeven",
              "Onderwerp": "Motie van het lid El Abassi over uitspreken dat gedupeerde gezinnen recht hebben op volledig herstel",
              "GestartOp": "2025-07-03T00:00:00+02:00",
              "Organisatie": "Tweede Kamer",
              "Grondslagvoorhang": null,
              "Termijn": null,
              "Vergaderjaar": "2024-2025",
              "Volgnummer": 40,
              "HuidigeBehandelstatus": null,
              "Afgedaan": true,
              "GrootProject": false,
              "GewijzigdOp": "2025-07-04T00:20:21.5+02:00",
              "ApiGewijzigdOp": "2025-07-08T08:12:02.8146857Z",
              "Verwijderd": false,
              "Kabinetsappreciatie": "Geen (expliciete) appreciatie"
            }
          ]
        }
      },
      "Fractie": {
        "Id": "a3689bb6-3914-4d5c-a6a8-42e24582e299",
        "Nummer": 2768,
        "Afkorting": "SP",
        "NaamNL": "Socialistische Partij",
        "NaamEN": "Socialist Party",
        "AantalZetels": 5,
        "AantalStemmen": 328225,
        "DatumActief": "1994-05-17T00:00:00+02:00",
        "DatumInactief": null,
        "ContentType": "image/png",
        "ContentLength": 2876,
        "GewijzigdOp": "2023-12-13T14:52:16+01:00",
        "ApiGewijzigdOp": "2023-12-13T13:53:22.1323118Z",
        "Verwijderd": false
      },
      "Persoon": null
    },
    {
      "Id": "30a249ff-288d-4c64-95e8-06435431f3aa",
      "Besluit_Id": "f670be55-8ccf-4da3-89a0-52d60b4e61de",
      "Soort": "Voor",
      "FractieGrootte": 5,
      "ActorNaam": "SP",
      "ActorFractie": "SP",
      "Vergissing": false,
      "SidActorLid": null,
      "SidActorFractie": "S-1-365867521-2120874753-3918075670-1133036099-4208265915-4115381510",
      "Persoon_Id": null,
      "Fractie_Id": "a3689bb6-3914-4d5c-a6a8-42e24582e299",
      "GewijzigdOp": "2025-07-04T11:20:34.953+02:00",
      "ApiGewijzigdOp": "2025-07-04T09:20:37.0377638Z",
      "Verwijderd": false,
      "Besluit": {
        "Id": "f670be55-8ccf-4da3-89a0-52d60b4e61de",
        "Agendapunt_Id": "12352374-cd3b-4b99-a6ab-232b3350b48b",
        "StemmingsSoort": "Met handopsteken",
        "BesluitSoort": "Stemmen - aangenomen",
        "BesluitTekst": "Aangenomen.",
        "Opmerking": null,
        "Status": "Besluit",
        "AgendapuntZaakBesluitVolgorde": 1,
        "GewijzigdOp": "2025-07-04T00:21:26.567+02:00",
        "ApiGewijzigdOp": "2025-07-03T22:21:30.1612456Z",
        "Verwijderd": false,
        "Agendapunt": {
          "Id": "12352374-cd3b-4b99-a6ab-232b3350b48b",
          "Nummer": "2025P13111",
          "Onderwerp": "Stemmingen over: moties ingediend bij het debat over de artikel 100-brief EUFOR Althea",
          "Aanvangstijd": null,
          "Eindtijd": null,
          "Volgorde": 14,
          "Rubriek": null,
          "Noot": null,
          "Status": "Vrijgegeven",
          "GewijzigdOp": "2025-07-03T21:20:59.47+02:00",
          "ApiGewijzigdOp": "2025-07-03T19:21:06.9290392Z",
          "Verwijderd": false,
          "Activiteit_Id": "6266b2a3-30c7-4fd7-bc81-145a3ef7c783",
          "Zaak": [
            {
              "Id": "273e6eeb-0e80-44fd-923f-1fea4d265fef",
              "Nummer": "2025Z14200",
              "Soort": "Motie",
              "Titel": "Nederlandse deelname aan vredesmissies",
              "Citeertitel": null,
              "Alias": null,
              "Status": "Vrijgegeven",
              "Onderwerp": "Motie van het lid Nordkamp over aansluiten bij sanctievoorstellen ter verdediging van de eenheid, veiligheid en stabiliteit van Bosnië en Herzegovina",
              "GestartOp": "2025-07-03T00:00:00+02:00",
              "Organisatie": "Tweede Kamer",
              "Grondslagvoorhang": null,
              "Termijn": null,
              "Vergaderjaar": "2024-2025",
              "Volgnummer": 499,
              "HuidigeBehandelstatus": null,
              "Afgedaan": true,
              "GrootProject": false,
              "GewijzigdOp": "2025-07-04T00:21:26.57+02:00",
              "ApiGewijzigdOp": "2025-07-08T08:11:58.1991756Z",
              "Verwijderd": false,
              "Kabinetsappreciatie": "Oordeel Kamer"
            },
            {
              "Id": "d3d454b6-daad-40cd-b45e-bd95692f330b",
              "Nummer": "2025Z14203",
              "Soort": "Motie",
              "Titel": "Nederlandse deelname aan vredesmissies",
              "Citeertitel": null,
              "Alias": null,
              "Status": "Vrijgegeven",
              "Onderwerp": "Motie van het lid Dobbe over zorgen dat vrouwelijke militairen toegang hebben tot passende scherfvesten ",
              "GestartOp": "2025-07-03T00:00:00+02:00",
              "Organisatie": "Tweede Kamer",
              "Grondslagvoorhang": null,
              "Termijn": null,
              "Vergaderjaar": "2024-2025",
              "Volgnummer": 501,
              "HuidigeBehandelstatus": null,
              "Afgedaan": true,
              "GrootProject": false,
              "GewijzigdOp": "2025-07-04T00:21:26.57+02:00",
              "ApiGewijzigdOp": "2025-07-08T08:21:14.2723279Z",
              "Verwijderd": false,
              "Kabinetsappreciatie": "Oordeel Kamer"
            },
            {
              "Id": "9559138b-e581-4ecf-adb2-fcf3e02982c6",
              "Nummer": "2025Z14202",
              "Soort": "Motie",
              "Titel": "Nederlandse deelname aan vredesmissies",
              "Citeertitel": null,
              "Alias": null,
              "Status": "Vrijgegeven",
              "Onderwerp": "Motie van de leden Dobbe en Paternotte over de bezuinigingen op het MATRA programma en het Stabiliteitsfonds in Bosnië en Herzegovina terugdraaien",
              "GestartOp": "2025-07-03T00:00:00+02:00",
              "Organisatie": "Tweede Kamer",
              "Grondslagvoorhang": null,
              "Termijn": null,
              "Vergaderjaar": "2024-2025",
              "Volgnummer": 500,
              "HuidigeBehandelstatus": null,
              "Afgedaan": true,
              "GrootProject": false,
              "GewijzigdOp": "2025-07-04T00:22:46.69+02:00",
              "ApiGewijzigdOp": "2025-07-08T08:11:54.7426195Z",
              "Verwijderd": false,
              "Kabinetsappreciatie": "Ontraden"
            }
          ]
        }
      },
      "Fractie": {
        "Id": "a3689bb6-3914-4d5c-a6a8-42e24582e299",
        "Nummer": 2768,
        "Afkorting": "SP",
        "NaamNL": "Socialistische Partij",
        "NaamEN": "Socialist Party",
        "AantalZetels": 5,
        "AantalStemmen": 328225,
        "DatumActief": "1994-05-17T00:00:00+02:00",
        "DatumInactief": null,
        "ContentType": "image/png",
        "ContentLength": 2876,
        "GewijzigdOp": "2023-12-13T14:52:16+01:00",
        "ApiGewijzigdOp": "2023-12-13T13:53:22.1323118Z",
        "Verwijderd": false
      },
      "Persoon": null
    },
    {
      "Id": "d7aadca1-1b7c-435d-82a7-0a1af0158c3e",
      "Besluit_Id": "eca9084a-5ba3-4b27-adb5-1b23d163b9cd",
      "Soort": "Voor",
      "FractieGrootte": 7,
      "ActorNaam": "BBB",
      "ActorFractie": "BBB",
      "Vergissing": false,
      "SidActorLid": null,
      "SidActorFractie": "S-1-365867521-2120874753-3989062109-1173306659-2208517255-2082135607",
      "Persoon_Id": null,
      "Fractie_Id": "626555ac-e836-44e3-9978-a6a7f0abc3ce",
      "GewijzigdOp": "2025-07-04T11:21:05.04+02:00",
      "ApiGewijzigdOp": "2025-07-04T09:21:09.0378376Z",
      "Verwijderd": false,
      "Besluit": {
        "Id": "eca9084a-5ba3-4b27-adb5-1b23d163b9cd",
        "Agendapunt_Id": "12352374-cd3b-4b99-a6ab-232b3350b48b",
        "StemmingsSoort": "Met handopsteken",
        "BesluitSoort": "Stemmen - aangenomen",
        "BesluitTekst": "Aangenomen.",
        "Opmerking": null,
        "Status": "Besluit",
        "AgendapuntZaakBesluitVolgorde": 3,
        "GewijzigdOp": "2025-07-04T00:21:26.567+02:00",
        "ApiGewijzigdOp": "2025-07-03T22:21:30.2181335Z",
        "Verwijderd": false,
        "Agendapunt": {
          "Id": "12352374-cd3b-4b99-a6ab-232b3350b48b",
          "Nummer": "2025P13111",
          "Onderwerp": "Stemmingen over: moties ingediend bij het debat over de artikel 100-brief EUFOR Althea",
          "Aanvangstijd": null,
          "Eindtijd": null,
          "Volgorde": 14,
          "Rubriek": null,
          "Noot": null,
          "Status": "Vrijgegeven",
          "GewijzigdOp": "2025-07-03T21:20:59.47+02:00",
          "ApiGewijzigdOp": "2025-07-03T19:21:06.9290392Z",
          "Verwijderd": false,
          "Activiteit_Id": "6266b2a3-30c7-4fd7-bc81-145a3ef7c783",
          "Zaak": [
            {
              "Id": "273e6eeb-0e80-44fd-923f-1fea4d265fef",
              "Nummer": "2025Z14200",
              "Soort": "Motie",
              "Titel": "Nederlandse deelname aan vredesmissies",
              "Citeertitel": null,
              "Alias": null,
              "Status": "Vrijgegeven",
              "Onderwerp": "Motie van het lid Nordkamp over aansluiten bij sanctievoorstellen ter verdediging van de eenheid, veiligheid en stabiliteit van Bosnië en Herzegovina",
              "GestartOp": "2025-07-03T00:00:00+02:00",
              "Organisatie": "Tweede Kamer",
              "Grondslagvoorhang": null,
              "Termijn": null,
              "Vergaderjaar": "2024-2025",
              "Volgnummer": 499,
              "HuidigeBehandelstatus": null,
              "Afgedaan": true,
              "GrootProject": false,
              "GewijzigdOp": "2025-07-04T00:21:26.57+02:00",
              "ApiGewijzigdOp": "2025-07-08T08:11:58.1991756Z",
              "Verwijderd": false,
              "Kabinetsappreciatie": "Oordeel Kamer"
            },
            {
              "Id": "d3d454b6-daad-40cd-b45e-bd95692f330b",
              "Nummer": "2025Z14203",
              "Soort": "Motie",
              "Titel": "Nederlandse deelname aan vredesmissies",
              "Citeertitel": null,
              "Alias": null,
              "Status": "Vrijgegeven",
              "Onderwerp": "Motie van het lid Dobbe over zorgen dat vrouwelijke militairen toegang hebben tot passende scherfvesten ",
              "GestartOp": "2025-07-03T00:00:00+02:00",
              "Organisatie": "Tweede Kamer",
              "Grondslagvoorhang": null,
              "Termijn": null,
              "Vergaderjaar": "2024-2025",
              "Volgnummer": 501,
              "HuidigeBehandelstatus": null,
              "Afgedaan": true,
              "GrootProject": false,
              "GewijzigdOp": "2025-07-04T00:21:26.57+02:00",
              "ApiGewijzigdOp": "2025-07-08T08:21:14.2723279Z",
              "Verwijderd": false,
              "Kabinetsappreciatie": "Oordeel Kamer"
            },
            {
              "Id": "9559138b-e581-4ecf-adb2-fcf3e02982c6",
              "Nummer": "2025Z14202",
              "Soort": "Motie",
              "Titel": "Nederlandse deelname aan vredesmissies",
              "Citeertitel": null,
              "Alias": null,
              "Status": "Vrijgegeven",
              "Onderwerp": "Motie van de leden Dobbe en Paternotte over de bezuinigingen op het MATRA programma en het Stabiliteitsfonds in Bosnië en Herzegovina terugdraaien",
              "GestartOp": "2025-07-03T00:00:00+02:00",
              "Organisatie": "Tweede Kamer",
              "Grondslagvoorhang": null,
              "Termijn": null,
              "Vergaderjaar": "2024-2025",
              "Volgnummer": 500,
              "HuidigeBehandelstatus": null,
              "Afgedaan": true,
              "GrootProject": false,
              "GewijzigdOp": "2025-07-04T00:22:46.69+02:00",
              "ApiGewijzigdOp": "2025-07-08T08:11:54.7426195Z",
              "Verwijderd": false,
              "Kabinetsappreciatie": "Ontraden"
            }
          ]
        }
      },
      "Fractie": {
        "Id": "626555ac-e836-44e3-9978-a6a7f0abc3ce",
        "Nummer": 50312,
        "Afkorting": "BBB",
        "NaamNL": "BoerBurgerBeweging",
        "NaamEN": "Farmer–Citizen Movement",
        "AantalZetels": 8,
        "AantalStemmen": 485551,
        "DatumActief": "2021-03-31T00:00:00+02:00",
        "DatumInactief": null,
        "ContentType": "image/jpeg",
        "ContentLength": 40024,
        "GewijzigdOp": "2025-07-31T11:24:15.3680679+02:00",
        "ApiGewijzigdOp": "2025-07-31T09:25:14.8678179Z",
        "Verwijderd": false
      },
      "Persoon": null
    },
    {
      "Id": "c7cdabc6-91b6-45ad-abeb-0271c2e21a2f",
      "Besluit_Id": "5be1cf74-57e3-4d61-8900-1983d26583d3",
      "Soort": "Voor",
      "FractieGrootte": 7,
      "ActorNaam": "BBB",
      "ActorFractie": "BBB",
      "Vergissing": false,
      "SidActorLid": null,
      "SidActorFractie": "S-1-365867521-2120874753-3989062109-1173306659-2208517255-2082135607",
      "Persoon_Id": null,
      "Fractie_Id": "626555ac-e836-44e3-9978-a6a7f0abc3ce",
      "GewijzigdOp": "2025-07-04T11:22:30.133+02:00",
      "ApiGewijzigdOp": "2025-07-04T09:22:36.8870267Z",
      "Verwijderd": false,
      "Besluit": {
        "Id": "5be1cf74-57e3-4d61-8900-1983d26583d3",
        "Agendapunt_Id": "83169fde-dc45-45f7-9c68-ffbfaea54936",
        "StemmingsSoort": "Met handopsteken",
        "BesluitSoort": "Stemmen - aangenomen",
        "BesluitTekst": "Aangenomen.",
        "Opmerking": null,
        "Status": "Besluit",
        "AgendapuntZaakBesluitVolgorde": 4,
        "GewijzigdOp": "2025-07-04T00:22:01.613+02:00",
        "ApiGewijzigdOp": "2025-07-03T22:22:05.9036299Z",
        "Verwijderd": false,
        "Agendapunt": {
          "Id": "83169fde-dc45-45f7-9c68-ffbfaea54936",
          "Nummer": "2025P13110",
          "Onderwerp": "Stemmingen over: moties ingediend bij het debat over kritiek op het onderzoek van de jeugdbescherming naar de eigen rol bij de toeslagenaffaire",
          "Aanvangstijd": null,
          "Eindtijd": null,
          "Volgorde": 13,
          "Rubriek": null,
          "Noot": null,
          "Status": "Vrijgegeven",
          "GewijzigdOp": "2025-07-03T20:42:16.107+02:00",
          "ApiGewijzigdOp": "2025-07-03T18:42:20.7554089Z",
          "Verwijderd": false,
          "Activiteit_Id": "6266b2a3-30c7-4fd7-bc81-145a3ef7c783",
          "Zaak": [
            {
              "Id": "09b56176-2205-4001-b67b-015cdfea30fe",
              "Nummer": "2025Z14190",
              "Soort": "Motie",
              "Titel": "Toeslagen",
              "Citeertitel": null,
              "Alias": null,
              "Status": "Vrijgegeven",
              "Onderwerp": "Motie van het lid Bruyning over binnen de jeugdbeschermingsketen een systemische en relationele benadering bevorderen waarin gezin, netwerk en herstel centraal staan",
              "GestartOp": "2025-07-03T00:00:00+02:00",
              "Organisatie": "Tweede Kamer",
              "Grondslagvoorhang": null,
              "Termijn": null,
              "Vergaderjaar": "2024-2025",
              "Volgnummer": 32,
              "HuidigeBehandelstatus": null,
              "Afgedaan": true,
              "GrootProject": false,
              "GewijzigdOp": "2025-07-04T00:22:01.617+02:00",
              "ApiGewijzigdOp": "2025-07-30T13:23:43.654163Z",
              "Verwijderd": false,
              "Kabinetsappreciatie": "Oordeel Kamer"
            },
            {
              "Id": "806bdf2d-63a0-46fd-887a-1453f3d63457",
              "Nummer": "2025Z14188",
              "Soort": "Motie",
              "Titel": "Toeslagen",
              "Citeertitel": null,
              "Alias": null,
              "Status": "Vrijgegeven",
              "Onderwerp": "Motie van het lid Ceder c.s. over instellen van een staatscommissie die onderzoek doet naar uithuisplaatsingen",
              "GestartOp": "2025-07-03T00:00:00+02:00",
              "Organisatie": "Tweede Kamer",
              "Grondslagvoorhang": null,
              "Termijn": null,
              "Vergaderjaar": "2024-2025",
              "Volgnummer": 30,
              "HuidigeBehandelstatus": null,
              "Afgedaan": true,
              "GrootProject": false,
              "GewijzigdOp": "2025-07-04T00:18:11.283+02:00",
              "ApiGewijzigdOp": "2025-07-08T08:05:07.9970551Z",
              "Verwijderd": false,
              "Kabinetsappreciatie": "Oordeel Kamer"
            },
            {
              "Id": "f2cc6907-af80-48bc-9675-192c9de4e29f",
              "Nummer": "2025Z14189",
              "Soort": "Motie",
              "Titel": "Toeslagen",
              "Citeertitel": null,
              "Alias": null,
              "Status": "Vrijgegeven",
              "Onderwerp": "Motie van het lid Bruyning over zich actief inzetten voor herstel voor ouders en kinderen die zijn geraakt door de toeslagenaffaire en uithuisplaatsingen",
              "GestartOp": "2025-07-03T00:00:00+02:00",
              "Organisatie": "Tweede Kamer",
              "Grondslagvoorhang": null,
              "Termijn": null,
              "Vergaderjaar": "2024-2025",
              "Volgnummer": 31,
              "HuidigeBehandelstatus": null,
              "Afgedaan": true,
              "GrootProject": false,
              "GewijzigdOp": "2025-07-04T00:22:01.617+02:00",
              "ApiGewijzigdOp": "2025-07-08T08:05:20.5666123Z",
              "Verwijderd": false,
              "Kabinetsappreciatie": "Oordeel Kamer"
            },
            {
              "Id": "20620d43-33cd-4e02-b4a4-1c3174aa5dd8",
              "Nummer": "2025Z14196",
              "Soort": "Motie",
              "Titel": "Toeslagen",
              "Citeertitel": null,
              "Alias": null,
              "Status": "Vrijgegeven",
              "Onderwerp": "Motie van het lid Crijns over verbieden dat organisaties die betrokken zijn bij ernstige misstanden in de toekomst nog zelfevaluaties uitvoeren zonder onafhankelijke externe toetsing of regie",
              "GestartOp": "2025-07-03T00:00:00+02:00",
              "Organisatie": "Tweede Kamer",
              "Grondslagvoorhang": null,
              "Termijn": null,
              "Vergaderjaar": "2024-2025",
              "Volgnummer": 38,
              "HuidigeBehandelstatus": null,
              "Afgedaan": true,
              "GrootProject": false,
              "GewijzigdOp": "2025-07-04T00:20:11.503+02:00",
              "ApiGewijzigdOp": "2025-07-08T08:05:30.7593368Z",
              "Verwijderd": false,
              "Kabinetsappreciatie": "Ontraden"
            },
            {
              "Id": "048a36e2-e687-4f32-9ca7-2eef58e13613",
              "Nummer": "2025Z14191",
              "Soort": "Motie",
              "Titel": "Toeslagen",
              "Citeertitel": null,
              "Alias": null,
              "Status": "Vrijgegeven",
              "Onderwerp": "Motie van het lid Inge van Dijk c.s. over een plan voor verbetering van de kindregeling die recht doet aan de behoefte van kinderen",
              "GestartOp": "2025-07-03T00:00:00+02:00",
              "Organisatie": "Tweede Kamer",
              "Grondslagvoorhang": null,
              "Termijn": null,
              "Vergaderjaar": "2024-2025",
              "Volgnummer": 33,
              "HuidigeBehandelstatus": null,
              "Afgedaan": true,
              "GrootProject": false,
              "GewijzigdOp": "2025-07-04T00:22:01.62+02:00",
              "ApiGewijzigdOp": "2025-07-08T08:05:20.580859Z",
              "Verwijderd": false,
              "Kabinetsappreciatie": "Oordeel Kamer"
            },
            {
              "Id": "bc26678f-772a-43eb-941f-321611a3f64f",
              "Nummer": "2025Z14194",
              "Soort": "Motie",
              "Titel": "Toeslagen",
              "Citeertitel": null,
              "Alias": null,
              "Status": "Vrijgegeven",
              "Onderwerp": "Motie van het lid Dijk over in kaart brengen hoeveel jongeren getroffen door het toeslagenschandaal een schuld bij DUO hebben ",
              "GestartOp": "2025-07-03T00:00:00+02:00",
              "Organisatie": "Tweede Kamer",
              "Grondslagvoorhang": null,
              "Termijn": null,
              "Vergaderjaar": "2024-2025",
              "Volgnummer": 36,
              "HuidigeBehandelstatus": null,
              "Afgedaan": true,
              "GrootProject": false,
              "GewijzigdOp": "2025-07-04T00:22:26.67+02:00",
              "ApiGewijzigdOp": "2025-07-08T08:05:30.7348034Z",
              "Verwijderd": false,
              "Kabinetsappreciatie": "Ontraden"
            },
            {
              "Id": "691bae2d-9fe9-45ec-b2c6-512a6667df18",
              "Nummer": "2025Z14195",
              "Soort": "Motie",
              "Titel": "Toeslagen",
              "Citeertitel": null,
              "Alias": null,
              "Status": "Vrijgegeven",
              "Onderwerp": "Motie van het lid Crijns over zorgen dat bestuurders die ernstig falen worden gedwongen tot aftreden en dat jeugdbeschermers die hun plicht ernstig verzaken worden ontslagen",
              "GestartOp": "2025-07-03T00:00:00+02:00",
              "Organisatie": "Tweede Kamer",
              "Grondslagvoorhang": null,
              "Termijn": null,
              "Vergaderjaar": "2024-2025",
              "Volgnummer": 37,
              "HuidigeBehandelstatus": null,
              "Afgedaan": true,
              "GrootProject": false,
              "GewijzigdOp": "2025-07-04T00:22:26.67+02:00",
              "ApiGewijzigdOp": "2025-07-08T08:05:30.7470143Z",
              "Verwijderd": false,
              "Kabinetsappreciatie": "Ontraden"
            },
            {
              "Id": "5d981dda-2ae5-4ad9-a373-5b74a3273993",
              "Nummer": "2025Z14187",
              "Soort": "Motie",
              "Titel": "Toeslagen",
              "Citeertitel": null,
              "Alias": null,
              "Status": "Vrijgegeven",
              "Onderwerp": "Motie van de leden Ceder en Bruyning over wettelijk verankeren dat terugplaatsing naar huis het uitgangspunt is bij uithuisplaatsingen",
              "GestartOp": "2025-07-03T00:00:00+02:00",
              "Organisatie": "Tweede Kamer",
              "Grondslagvoorhang": null,
              "Termijn": null,
              "Vergaderjaar": "2024-2025",
              "Volgnummer": 29,
              "HuidigeBehandelstatus": null,
              "Afgedaan": true,
              "GrootProject": false,
              "GewijzigdOp": "2025-07-04T00:18:11.283+02:00",
              "ApiGewijzigdOp": "2025-07-08T08:05:04.8660488Z",
              "Verwijderd": false,
              "Kabinetsappreciatie": "Oordeel Kamer"
            },
            {
              "Id": "185d08a6-8d5c-4b3b-b6ae-7dc65d48b861",
              "Nummer": "2025Z14192",
              "Soort": "Motie",
              "Titel": "Toeslagen",
              "Citeertitel": null,
              "Alias": null,
              "Status": "Vrijgegeven",
              "Onderwerp": "Motie van het lid Westerveld over een tijdlijn met duidelijke deadlines en een concrete uitwerking van de ondersteuningsmaatregelen inclusief financiële dekking ",
              "GestartOp": "2025-07-03T00:00:00+02:00",
              "Organisatie": "Tweede Kamer",
              "Grondslagvoorhang": null,
              "Termijn": null,
              "Vergaderjaar": "2024-2025",
              "Volgnummer": 34,
              "HuidigeBehandelstatus": null,
              "Afgedaan": true,
              "GrootProject": false,
              "GewijzigdOp": "2025-07-04T00:22:01.62+02:00",
              "ApiGewijzigdOp": "2025-07-08T08:03:27.9122114Z",
              "Verwijderd": false,
              "Kabinetsappreciatie": "Oordeel Kamer"
            },
            {
              "Id": "edf9b224-f388-445d-947e-9bf419345a60",
              "Nummer": "2025Z14197",
              "Soort": "Motie",
              "Titel": "Toeslagen",
              "Citeertitel": null,
              "Alias": null,
              "Status": "Vrijgegeven",
              "Onderwerp": "Motie van het lid El Abassi over uitspreken dat pas recht gedaan kan worden aan het leed van gedupeerde gezinnen als alle betrokken ketenpartners openlijk verantwoordelijkheid nemen voor hun rol in de toeslagenaffaire",
              "GestartOp": "2025-07-03T00:00:00+02:00",
              "Organisatie": "Tweede Kamer",
              "Grondslagvoorhang": null,
              "Termijn": null,
              "Vergaderjaar": "2024-2025",
              "Volgnummer": 39,
              "HuidigeBehandelstatus": null,
              "Afgedaan": true,
              "GrootProject": false,
              "GewijzigdOp": "2025-07-04T00:20:11.507+02:00",
              "ApiGewijzigdOp": "2025-07-08T08:11:32.0215713Z",
              "Verwijderd": false,
              "Kabinetsappreciatie": "Geen (expliciete) appreciatie"
            },
            {
              "Id": "27c431c2-7bfb-42d1-92f5-a666cc41dc72",
              "Nummer": "2025Z14193",
              "Soort": "Motie",
              "Titel": "Toeslagen",
              "Citeertitel": null,
              "Alias": null,
              "Status": "Vrijgegeven",
              "Onderwerp": "Motie van het lid Dijk over het kwijtschelden van DUO-schulden van gedupeerde jongeren die zijn gebruikt om hun ouders te helpen",
              "GestartOp": "2025-07-03T00:00:00+02:00",
              "Organisatie": "Tweede Kamer",
              "Grondslagvoorhang": null,
              "Termijn": null,
              "Vergaderjaar": "2024-2025",
              "Volgnummer": 35,
              "HuidigeBehandelstatus": null,
              "Afgedaan": true,
              "GrootProject": false,
              "GewijzigdOp": "2025-07-04T00:22:26.667+02:00",
              "ApiGewijzigdOp": "2025-07-08T08:05:21.6774175Z",
              "Verwijderd": false,
              "Kabinetsappreciatie": "Ontraden"
            },
            {
              "Id": "1c60ed97-30a9-4d0b-93ce-d0080fe1d7f3",
              "Nummer": "2025Z14198",
              "Soort": "Motie",
              "Titel": "Toeslagen",
              "Citeertitel": null,
              "Alias": null,
              "Status": "Vrijgegeven",
              "Onderwerp": "Motie van het lid El Abassi over uitspreken dat gedupeerde gezinnen recht hebben op volledig herstel",
              "GestartOp": "2025-07-03T00:00:00+02:00",
              "Organisatie": "Tweede Kamer",
              "Grondslagvoorhang": null,
              "Termijn": null,
              "Vergaderjaar": "2024-2025",
              "Volgnummer": 40,
              "HuidigeBehandelstatus": null,
              "Afgedaan": true,
              "GrootProject": false,
              "GewijzigdOp": "2025-07-04T00:20:21.5+02:00",
              "ApiGewijzigdOp": "2025-07-08T08:12:02.8146857Z",
              "Verwijderd": false,
              "Kabinetsappreciatie": "Geen (expliciete) appreciatie"
            }
          ]
        }
      },
      "Fractie": {
        "Id": "626555ac-e836-44e3-9978-a6a7f0abc3ce",
        "Nummer": 50312,
        "Afkorting": "BBB",
        "NaamNL": "BoerBurgerBeweging",
        "NaamEN": "Farmer–Citizen Movement",
        "AantalZetels": 8,
        "AantalStemmen": 485551,
        "DatumActief": "2021-03-31T00:00:00+02:00",
        "DatumInactief": null,
        "ContentType": "image/jpeg",
        "ContentLength": 40024,
        "GewijzigdOp": "2025-07-31T11:24:15.3680679+02:00",
        "ApiGewijzigdOp": "2025-07-31T09:25:14.8678179Z",
        "Verwijderd": false
      },
      "Persoon": null
    },
    {
      "Id": "f8a1ee08-5ed3-42e6-ace4-04da6f6c7ff2",
      "Besluit_Id": "cca9cf20-21bd-4a5c-b7b5-617259eb2902",
      "Soort": "Voor",
      "FractieGrootte": 7,
      "ActorNaam": "BBB",
      "ActorFractie": "BBB",
      "Vergissing": false,
      "SidActorLid": null,
      "SidActorFractie": "S-1-365867521-2120874753-3989062109-1173306659-2208517255-2082135607",
      "Persoon_Id": null,
      "Fractie_Id": "626555ac-e836-44e3-9978-a6a7f0abc3ce",
      "GewijzigdOp": "2025-07-04T11:22:25.14+02:00",
      "ApiGewijzigdOp": "2025-07-04T09:22:32.6036202Z",
      "Verwijderd": false,
      "Besluit": {
        "Id": "cca9cf20-21bd-4a5c-b7b5-617259eb2902",
        "Agendapunt_Id": "83169fde-dc45-45f7-9c68-ffbfaea54936",
        "StemmingsSoort": "Met handopsteken",
        "BesluitSoort": "Stemmen - aangenomen",
        "BesluitTekst": "Aangenomen.",
        "Opmerking": null,
        "Status": "Besluit",
        "AgendapuntZaakBesluitVolgorde": 3,
        "GewijzigdOp": "2025-07-04T00:22:01.613+02:00",
        "ApiGewijzigdOp": "2025-07-03T22:22:05.9142409Z",
        "Verwijderd": false,
        "Agendapunt": {
          "Id": "83169fde-dc45-45f7-9c68-ffbfaea54936",
          "Nummer": "2025P13110",
          "Onderwerp": "Stemmingen over: moties ingediend bij het debat over kritiek op het onderzoek van de jeugdbescherming naar de eigen rol bij de toeslagenaffaire",
          "Aanvangstijd": null,
          "Eindtijd": null,
          "Volgorde": 13,
          "Rubriek": null,
          "Noot": null,
          "Status": "Vrijgegeven",
          "GewijzigdOp": "2025-07-03T20:42:16.107+02:00",
          "ApiGewijzigdOp": "2025-07-03T18:42:20.7554089Z",
          "Verwijderd": false,
          "Activiteit_Id": "6266b2a3-30c7-4fd7-bc81-145a3ef7c783",
          "Zaak": [
            {
              "Id": "09b56176-2205-4001-b67b-015cdfea30fe",
              "Nummer": "2025Z14190",
              "Soort": "Motie",
              "Titel": "Toeslagen",
              "Citeertitel": null,
              "Alias": null,
              "Status": "Vrijgegeven",
              "Onderwerp": "Motie van het lid Bruyning over binnen de jeugdbeschermingsketen een systemische en relationele benadering bevorderen waarin gezin, netwerk en herstel centraal staan",
              "GestartOp": "2025-07-03T00:00:00+02:00",
              "Organisatie": "Tweede Kamer",
              "Grondslagvoorhang": null,
              "Termijn": null,
              "Vergaderjaar": "2024-2025",
              "Volgnummer": 32,
              "HuidigeBehandelstatus": null,
              "Afgedaan": true,
              "GrootProject": false,
              "GewijzigdOp": "2025-07-04T00:22:01.617+02:00",
              "ApiGewijzigdOp": "2025-07-30T13:23:43.654163Z",
              "Verwijderd": false,
              "Kabinetsappreciatie": "Oordeel Kamer"
            },
            {
              "Id": "806bdf2d-63a0-46fd-887a-1453f3d63457",
              "Nummer": "2025Z14188",
              "Soort": "Motie",
              "Titel": "Toeslagen",
              "Citeertitel": null,
              "Alias": null,
              "Status": "Vrijgegeven",
              "Onderwerp": "Motie van het lid Ceder c.s. over instellen van een staatscommissie die onderzoek doet naar uithuisplaatsingen",
              "GestartOp": "2025-07-03T00:00:00+02:00",
              "Organisatie": "Tweede Kamer",
              "Grondslagvoorhang": null,
              "Termijn": null,
              "Vergaderjaar": "2024-2025",
              "Volgnummer": 30,
              "HuidigeBehandelstatus": null,
              "Afgedaan": true,
              "GrootProject": false,
              "GewijzigdOp": "2025-07-04T00:18:11.283+02:00",
              "ApiGewijzigdOp": "2025-07-08T08:05:07.9970551Z",
              "Verwijderd": false,
              "Kabinetsappreciatie": "Oordeel Kamer"
            },
            {
              "Id": "f2cc6907-af80-48bc-9675-192c9de4e29f",
              "Nummer": "2025Z14189",
              "Soort": "Motie",
              "Titel": "Toeslagen",
              "Citeertitel": null,
              "Alias": null,
              "Status": "Vrijgegeven",
              "Onderwerp": "Motie van het lid Bruyning over zich actief inzetten voor herstel voor ouders en kinderen die zijn geraakt door de toeslagenaffaire en uithuisplaatsingen",
              "GestartOp": "2025-07-03T00:00:00+02:00",
              "Organisatie": "Tweede Kamer",
              "Grondslagvoorhang": null,
              "Termijn": null,
              "Vergaderjaar": "2024-2025",
              "Volgnummer": 31,
              "HuidigeBehandelstatus": null,
              "Afgedaan": true,
              "GrootProject": false,
              "GewijzigdOp": "2025-07-04T00:22:01.617+02:00",
              "ApiGewijzigdOp": "2025-07-08T08:05:20.5666123Z",
              "Verwijderd": false,
              "Kabinetsappreciatie": "Oordeel Kamer"
            },
            {
              "Id": "20620d43-33cd-4e02-b4a4-1c3174aa5dd8",
              "Nummer": "2025Z14196",
              "Soort": "Motie",
              "Titel": "Toeslagen",
              "Citeertitel": null,
              "Alias": null,
              "Status": "Vrijgegeven",
              "Onderwerp": "Motie van het lid Crijns over verbieden dat organisaties die betrokken zijn bij ernstige misstanden in de toekomst nog zelfevaluaties uitvoeren zonder onafhankelijke externe toetsing of regie",
              "GestartOp": "2025-07-03T00:00:00+02:00",
              "Organisatie": "Tweede Kamer",
              "Grondslagvoorhang": null,
              "Termijn": null,
              "Vergaderjaar": "2024-2025",
              "Volgnummer": 38,
              "HuidigeBehandelstatus": null,
              "Afgedaan": true,
              "GrootProject": false,
              "GewijzigdOp": "2025-07-04T00:20:11.503+02:00",
              "ApiGewijzigdOp": "2025-07-08T08:05:30.7593368Z",
              "Verwijderd": false,
              "Kabinetsappreciatie": "Ontraden"
            },
            {
              "Id": "048a36e2-e687-4f32-9ca7-2eef58e13613",
              "Nummer": "2025Z14191",
              "Soort": "Motie",
              "Titel": "Toeslagen",
              "Citeertitel": null,
              "Alias": null,
              "Status": "Vrijgegeven",
              "Onderwerp": "Motie van het lid Inge van Dijk c.s. over een plan voor verbetering van de kindregeling die recht doet aan de behoefte van kinderen",
              "GestartOp": "2025-07-03T00:00:00+02:00",
              "Organisatie": "Tweede Kamer",
              "Grondslagvoorhang": null,
              "Termijn": null,
              "Vergaderjaar": "2024-2025",
              "Volgnummer": 33,
              "HuidigeBehandelstatus": null,
              "Afgedaan": true,
              "GrootProject": false,
              "GewijzigdOp": "2025-07-04T00:22:01.62+02:00",
              "ApiGewijzigdOp": "2025-07-08T08:05:20.580859Z",
              "Verwijderd": false,
              "Kabinetsappreciatie": "Oordeel Kamer"
            },
            {
              "Id": "bc26678f-772a-43eb-941f-321611a3f64f",
              "Nummer": "2025Z14194",
              "Soort": "Motie",
              "Titel": "Toeslagen",
              "Citeertitel": null,
              "Alias": null,
              "Status": "Vrijgegeven",
              "Onderwerp": "Motie van het lid Dijk over in kaart brengen hoeveel jongeren getroffen door het toeslagenschandaal een schuld bij DUO hebben ",
              "GestartOp": "2025-07-03T00:00:00+02:00",
              "Organisatie": "Tweede Kamer",
              "Grondslagvoorhang": null,
              "Termijn": null,
              "Vergaderjaar": "2024-2025",
              "Volgnummer": 36,
              "HuidigeBehandelstatus": null,
              "Afgedaan": true,
              "GrootProject": false,
              "GewijzigdOp": "2025-07-04T00:22:26.67+02:00",
              "ApiGewijzigdOp": "2025-07-08T08:05:30.7348034Z",
              "Verwijderd": false,
              "Kabinetsappreciatie": "Ontraden"
            },
            {
              "Id": "691bae2d-9fe9-45ec-b2c6-512a6667df18",
              "Nummer": "2025Z14195",
              "Soort": "Motie",
              "Titel": "Toeslagen",
              "Citeertitel": null,
              "Alias": null,
              "Status": "Vrijgegeven",
              "Onderwerp": "Motie van het lid Crijns over zorgen dat bestuurders die ernstig falen worden gedwongen tot aftreden en dat jeugdbeschermers die hun plicht ernstig verzaken worden ontslagen",
              "GestartOp": "2025-07-03T00:00:00+02:00",
              "Organisatie": "Tweede Kamer",
              "Grondslagvoorhang": null,
              "Termijn": null,
              "Vergaderjaar": "2024-2025",
              "Volgnummer": 37,
              "HuidigeBehandelstatus": null,
              "Afgedaan": true,
              "GrootProject": false,
              "GewijzigdOp": "2025-07-04T00:22:26.67+02:00",
              "ApiGewijzigdOp": "2025-07-08T08:05:30.7470143Z",
              "Verwijderd": false,
              "Kabinetsappreciatie": "Ontraden"
            },
            {
              "Id": "5d981dda-2ae5-4ad9-a373-5b74a3273993",
              "Nummer": "2025Z14187",
              "Soort": "Motie",
              "Titel": "Toeslagen",
              "Citeertitel": null,
              "Alias": null,
              "Status": "Vrijgegeven",
              "Onderwerp": "Motie van de leden Ceder en Bruyning over wettelijk verankeren dat terugplaatsing naar huis het uitgangspunt is bij uithuisplaatsingen",
              "GestartOp": "2025-07-03T00:00:00+02:00",
              "Organisatie": "Tweede Kamer",
              "Grondslagvoorhang": null,
              "Termijn": null,
              "Vergaderjaar": "2024-2025",
              "Volgnummer": 29,
              "HuidigeBehandelstatus": null,
              "Afgedaan": true,
              "GrootProject": false,
              "GewijzigdOp": "2025-07-04T00:18:11.283+02:00",
              "ApiGewijzigdOp": "2025-07-08T08:05:04.8660488Z",
              "Verwijderd": false,
              "Kabinetsappreciatie": "Oordeel Kamer"
            },
            {
              "Id": "185d08a6-8d5c-4b3b-b6ae-7dc65d48b861",
              "Nummer": "2025Z14192",
              "Soort": "Motie",
              "Titel": "Toeslagen",
              "Citeertitel": null,
              "Alias": null,
              "Status": "Vrijgegeven",
              "Onderwerp": "Motie van het lid Westerveld over een tijdlijn met duidelijke deadlines en een concrete uitwerking van de ondersteuningsmaatregelen inclusief financiële dekking ",
              "GestartOp": "2025-07-03T00:00:00+02:00",
              "Organisatie": "Tweede Kamer",
              "Grondslagvoorhang": null,
              "Termijn": null,
              "Vergaderjaar": "2024-2025",
              "Volgnummer": 34,
              "HuidigeBehandelstatus": null,
              "Afgedaan": true,
              "GrootProject": false,
              "GewijzigdOp": "2025-07-04T00:22:01.62+02:00",
              "ApiGewijzigdOp": "2025-07-08T08:03:27.9122114Z",
              "Verwijderd": false,
              "Kabinetsappreciatie": "Oordeel Kamer"
            },
            {
              "Id": "edf9b224-f388-445d-947e-9bf419345a60",
              "Nummer": "2025Z14197",
              "Soort": "Motie",
              "Titel": "Toeslagen",
              "Citeertitel": null,
              "Alias": null,
              "Status": "Vrijgegeven",
              "Onderwerp": "Motie van het lid El Abassi over uitspreken dat pas recht gedaan kan worden aan het leed van gedupeerde gezinnen als alle betrokken ketenpartners openlijk verantwoordelijkheid nemen voor hun rol in de toeslagenaffaire",
              "GestartOp": "2025-07-03T00:00:00+02:00",
              "Organisatie": "Tweede Kamer",
              "Grondslagvoorhang": null,
              "Termijn": null,
              "Vergaderjaar": "2024-2025",
              "Volgnummer": 39,
              "HuidigeBehandelstatus": null,
              "Afgedaan": true,
              "GrootProject": false,
              "GewijzigdOp": "2025-07-04T00:20:11.507+02:00",
              "ApiGewijzigdOp": "2025-07-08T08:11:32.0215713Z",
              "Verwijderd": false,
              "Kabinetsappreciatie": "Geen (expliciete) appreciatie"
            },
            {
              "Id": "27c431c2-7bfb-42d1-92f5-a666cc41dc72",
              "Nummer": "2025Z14193",
              "Soort": "Motie",
              "Titel": "Toeslagen",
              "Citeertitel": null,
              "Alias": null,
              "Status": "Vrijgegeven",
              "Onderwerp": "Motie van het lid Dijk over het kwijtschelden van DUO-schulden van gedupeerde jongeren die zijn gebruikt om hun ouders te helpen",
              "GestartOp": "2025-07-03T00:00:00+02:00",
              "Organisatie": "Tweede Kamer",
              "Grondslagvoorhang": null,
              "Termijn": null,
              "Vergaderjaar": "2024-2025",
              "Volgnummer": 35,
              "HuidigeBehandelstatus": null,
              "Afgedaan": true,
              "GrootProject": false,
              "GewijzigdOp": "2025-07-04T00:22:26.667+02:00",
              "ApiGewijzigdOp": "2025-07-08T08:05:21.6774175Z",
              "Verwijderd": false,
              "Kabinetsappreciatie": "Ontraden"
            },
            {
              "Id": "1c60ed97-30a9-4d0b-93ce-d0080fe1d7f3",
              "Nummer": "2025Z14198",
              "Soort": "Motie",
              "Titel": "Toeslagen",
              "Citeertitel": null,
              "Alias": null,
              "Status": "Vrijgegeven",
              "Onderwerp": "Motie van het lid El Abassi over uitspreken dat gedupeerde gezinnen recht hebben op volledig herstel",
              "GestartOp": "2025-07-03T00:00:00+02:00",
              "Organisatie": "Tweede Kamer",
              "Grondslagvoorhang": null,
              "Termijn": null,
              "Vergaderjaar": "2024-2025",
              "Volgnummer": 40,
              "HuidigeBehandelstatus": null,
              "Afgedaan": true,
              "GrootProject": false,
              "GewijzigdOp": "2025-07-04T00:20:21.5+02:00",
              "ApiGewijzigdOp": "2025-07-08T08:12:02.8146857Z",
              "Verwijderd": false,
              "Kabinetsappreciatie": "Geen (expliciete) appreciatie"
            }
          ]
        }
      },
      "Fractie": {
        "Id": "626555ac-e836-44e3-9978-a6a7f0abc3ce",
        "Nummer": 50312,
        "Afkorting": "BBB",
        "NaamNL": "BoerBurgerBeweging",
        "NaamEN": "Farmer–Citizen Movement",
        "AantalZetels": 8,
        "AantalStemmen": 485551,
        "DatumActief": "2021-03-31T00:00:00+02:00",
        "DatumInactief": null,
        "ContentType": "image/jpeg",
        "ContentLength": 40024,
        "GewijzigdOp": "2025-07-31T11:24:15.3680679+02:00",
        "ApiGewijzigdOp": "2025-07-31T09:25:14.8678179Z",
        "Verwijderd": false
      },
      "Persoon": null
    }
  ]
}